{
  "schema_version": 1,
  "generated_at": "2026-07-23T11:37:02Z",
  "scope": "animation_category_name_level_split_review",
  "summary": {
    "split_review_categories": 2,
    "affected_catalog_rows": 110,
    "candidate_split_rules": 0,
    "matched_sample_names": 0,
    "unmatched_sample_names": 9,
    "catalog_scan_enabled": true,
    "catalog_source_category_rows": 2465,
    "matched_catalog_rule_hits": 0,
    "matched_catalog_rows": 0,
    "unmatched_catalog_rows": 2465,
    "by_target_family": [],
    "candidate_priority_rows": 0,
    "starter_confirmed_queue_rows": 0,
    "top_candidate_expected_update_rows": 0,
    "top_candidate_source_category": null,
    "top_candidate_target_category": null,
    "manual_confirmed_rows": 0,
    "auto_apply_enabled": false
  },
  "review_items": [
    {
      "source_category": "굿즈",
      "affected_catalog_rows": 109,
      "catalog_category_rows": 2444,
      "suggested_default_category": "기타 굿즈",
      "review_reason": "Broad catch-all category; inspect names before moving to a specific folder family.",
      "sample_names": [
        "一番くじ 葬送のフリーレン - B賞 メタリックビジュアルシート",
        "一番くじ 葬送のフリーレン - G賞 魔導書風ノート",
        "一番くじ 呪術廻戦 死滅回游 ～弐～ - L賞 ぽこっとちゃーむ",
        "一番くじ 僕のヒーローアカデミア -紡がれる想い- - F-1賞 SOFVICちゅ 緑谷出久",
        "一番くじ 僕のヒーローアカデミア -紡がれる想い- - F-2賞 SOFVICちゅ 爆豪勝己",
        "一番くじ 僕のヒーローアカデミア -紡がれる想い- - F-3賞 SOFVICちゅ 麗日お茶子",
        "一番くじ 僕のヒーローアカデミア -紡がれる想い- - F-4賞 SOFVICちゅ 轟焦凍",
        "一番くじ 僕のヒーローアカデミア -紡がれる想い- - F-5賞 SOFVICちゅ オールマイト"
      ],
      "split_candidate_count": 0,
      "matched_sample_count": 0,
      "unmatched_sample_count": 8,
      "matched_catalog_rule_hit_count": 0,
      "matched_catalog_row_count": 0,
      "unmatched_catalog_row_count": 2444,
      "split_candidates": [],
      "unmatched_sample_names": [
        "一番くじ 葬送のフリーレン - B賞 メタリックビジュアルシート",
        "一番くじ 葬送のフリーレン - G賞 魔導書風ノート",
        "一番くじ 呪術廻戦 死滅回游 ～弐～ - L賞 ぽこっとちゃーむ",
        "一番くじ 僕のヒーローアカデミア -紡がれる想い- - F-1賞 SOFVICちゅ 緑谷出久",
        "一番くじ 僕のヒーローアカデミア -紡がれる想い- - F-2賞 SOFVICちゅ 爆豪勝己",
        "一番くじ 僕のヒーローアカデミア -紡がれる想い- - F-3賞 SOFVICちゅ 麗日お茶子",
        "一番くじ 僕のヒーローアカデミア -紡がれる想い- - F-4賞 SOFVICちゅ 轟焦凍",
        "一番くじ 僕のヒーローアカデミア -紡がれる想い- - F-5賞 SOFVICちゅ オールマイト"
      ],
      "unmatched_catalog_samples": [
        {
          "catalog_index": 2532,
          "name_ko": "치이카와 영화 \"치이카와\" 시루코 샌드",
          "name_ja": "ちいかわ 映画ちいかわ しるこサンド",
          "category": "굿즈",
          "affiliation": "치이카와",
          "series_name": "치이카와 마켓",
          "sub_series": "공식 마켓",
          "source_store": "치이카와 마켓"
        },
        {
          "catalog_index": 2546,
          "name_ko": "치이카와 그 시절의 카메라 (토끼 브이)",
          "name_ja": "ちいかわ あのころのカメラ（うさぎ ピース）",
          "category": "굿즈",
          "affiliation": "치이카와",
          "series_name": "치이카와 마켓",
          "sub_series": "공식 마켓",
          "source_store": "치이카와 마켓"
        },
        {
          "catalog_index": 2547,
          "name_ko": "치이카와 그 시절의 카메라 (가르마 브이)",
          "name_ja": "ちいかわ あのころのカメラ（ハチワレ ピース）",
          "category": "굿즈",
          "affiliation": "치이카와",
          "series_name": "치이카와 마켓",
          "sub_series": "공식 마켓",
          "source_store": "치이카와 마켓"
        },
        {
          "catalog_index": 2548,
          "name_ko": "치이카와 그 시절의 카메라 (치이카와 브이)",
          "name_ja": "ちいかわ あのころのカメラ（ちいかわ ピース）",
          "category": "굿즈",
          "affiliation": "치이카와",
          "series_name": "치이카와 마켓",
          "sub_series": "공식 마켓",
          "source_store": "치이카와 마켓"
        },
        {
          "catalog_index": 2549,
          "name_ko": "치이카와 그 시절의 카메라 (모두)",
          "name_ja": "ちいかわ あのころのカメラ（みんな）",
          "category": "굿즈",
          "affiliation": "치이카와",
          "series_name": "치이카와 마켓",
          "sub_series": "공식 마켓",
          "source_store": "치이카와 마켓"
        },
        {
          "catalog_index": 2605,
          "name_ko": "치이카와 영화 \"치이카와\" 슈슈 모두 라이트 옐로",
          "name_ja": "ちいかわ 映画ちいかわ シュシュ みんな ライトイエロー",
          "category": "굿즈",
          "affiliation": "치이카와",
          "series_name": "치이카와 마켓",
          "sub_series": "공식 마켓",
          "source_store": "치이카와 마켓"
        },
        {
          "catalog_index": 2606,
          "name_ko": "치이카와 영화 \"치이카와\" 슈슈 세이렌 핑크",
          "name_ja": "ちいかわ 映画ちいかわ シュシュ セイレーン ピンク",
          "category": "굿즈",
          "affiliation": "치이카와",
          "series_name": "치이카와 마켓",
          "sub_series": "공식 마켓",
          "source_store": "치이카와 마켓"
        },
        {
          "catalog_index": 2607,
          "name_ko": "치이카와 영화 \"치이카와\" 스니커즈 양말 시마지로 그레이 22-24cm",
          "name_ja": "ちいかわ 映画ちいかわ スニーカーソックス 島二郎 グレー 22-24cm",
          "category": "굿즈",
          "affiliation": "치이카와",
          "series_name": "치이카와 마켓",
          "sub_series": "공식 마켓",
          "source_store": "치이카와 마켓"
        }
      ],
      "manual_confirmation_template": "server/animation_category_name_split_confirmed_rows.template.json",
      "confirmed_queue": "server/animation_category_name_split_confirmed_rows.json",
      "import_tool": "tools/import_confirmed_animation_category_rows.py",
      "unblocks_when": "name_level_split_manually_confirmed",
      "auto_apply_enabled": false
    },
    {
      "source_category": "아크릴",
      "affected_catalog_rows": 1,
      "catalog_category_rows": 21,
      "suggested_default_category": "아크릴 스탠드",
      "review_reason": "Most acrylic goods should be split into acrylic stand/keyholder/card after name review.",
      "sample_names": [
        "一番くじ 僕のヒーローアカデミア～ジャンフェス限定!～ - B賞 アクリルストラップ"
      ],
      "split_candidate_count": 0,
      "matched_sample_count": 0,
      "unmatched_sample_count": 1,
      "matched_catalog_rule_hit_count": 0,
      "matched_catalog_row_count": 0,
      "unmatched_catalog_row_count": 21,
      "split_candidates": [],
      "unmatched_sample_names": [
        "一番くじ 僕のヒーローアカデミア～ジャンフェス限定!～ - B賞 アクリルストラップ"
      ],
      "unmatched_catalog_samples": [
        {
          "catalog_index": 9473,
          "name_ko": "치이카와 천사 & 악마 2WAY 피크릴 스탠드 (②악마)",
          "name_ja": "ちいかわ てんし♡あくま 2WAY ピックリルスタンド（②あくま）",
          "category": "아크릴",
          "affiliation": "치이카와",
          "series_name": "치이카와 마켓",
          "sub_series": "공식 마켓",
          "source_store": "치이카와 마켓"
        },
        {
          "catalog_index": 9474,
          "name_ko": "치이카와 천사 & 악마 2WAY 피크릴 스탠드 (①천사)",
          "name_ja": "ちいかわ てんし♡あくま 2WAY ピックリルスタンド（①てんし）",
          "category": "아크릴",
          "affiliation": "치이카와",
          "series_name": "치이카와 마켓",
          "sub_series": "공식 마켓",
          "source_store": "치이카와 마켓"
        },
        {
          "catalog_index": 9860,
          "name_ko": "치이카와 2WAY 피크릴 스탠드 (④버섯 먹지 마!!)",
          "name_ja": "ちいかわ 2WAY ピックリルスタンド（④キノコ食べるな！！）",
          "category": "아크릴",
          "affiliation": "치이카와",
          "series_name": "치이카와 마켓",
          "sub_series": "공식 마켓",
          "source_store": "치이카와 마켓"
        },
        {
          "catalog_index": 9861,
          "name_ko": "치이카와 2WAY 피크릴 스탠드 (③츳빠빠빠)",
          "name_ja": "ちいかわ 2WAY ピックリルスタンド（③つっぱっぱっぱっ）",
          "category": "아크릴",
          "affiliation": "치이카와",
          "series_name": "치이카와 마켓",
          "sub_series": "공식 마켓",
          "source_store": "치이카와 마켓"
        },
        {
          "catalog_index": 9862,
          "name_ko": "치이카와 2WAY 피크릴 스탠드 (②노래하기 좋은 날)",
          "name_ja": "ちいかわ 2WAY ピックリルスタンド（②うた日和）",
          "category": "아크릴",
          "affiliation": "치이카와",
          "series_name": "치이카와 마켓",
          "sub_series": "공식 마켓",
          "source_store": "치이카와 마켓"
        },
        {
          "catalog_index": 9863,
          "name_ko": "치이카와 2WAY 피크릴 스탠드 (①요정이 되어버렸어)",
          "name_ja": "ちいかわ 2WAY ピックリルスタンド（①妖精になっちゃった）",
          "category": "아크릴",
          "affiliation": "치이카와",
          "series_name": "치이카와 마켓",
          "sub_series": "공식 마켓",
          "source_store": "치이카와 마켓"
        },
        {
          "catalog_index": 12504,
          "name_ko": "一番くじ Pokémon 30th ANNIVERSARY vol.1 - A賞 30周年記念アクリル時計",
          "name_ja": "A賞 30周年記念アクリル時計",
          "category": "아크릴",
          "affiliation": "포켓몬",
          "series_name": "一番くじ Pokémon 30th ANNIVERSARY vol.1",
          "sub_series": "A賞",
          "source_store": "이치방쿠지"
        },
        {
          "catalog_index": 12524,
          "name_ko": "一番くじ 勝利の女神：NIKKE CHAPTER7 - J賞 アクリルコースター",
          "name_ja": "J賞 アクリルコースター",
          "category": "아크릴",
          "affiliation": "승리의 여신: 니케",
          "series_name": "一番くじ 勝利の女神：NIKKE CHAPTER7",
          "sub_series": "J賞",
          "source_store": "이치방쿠지"
        }
      ],
      "manual_confirmation_template": "server/animation_category_name_split_confirmed_rows.template.json",
      "confirmed_queue": "server/animation_category_name_split_confirmed_rows.json",
      "import_tool": "tools/import_confirmed_animation_category_rows.py",
      "unblocks_when": "name_level_split_manually_confirmed",
      "auto_apply_enabled": false
    }
  ],
  "candidate_priority_queue": [],
  "starter_confirmed_queue": {
    "schema_version": 1,
    "source_report": "data/animation_category_split_review_public.json",
    "target_queue": "server/animation_category_name_split_confirmed_rows.json",
    "import_tool": "tools/import_confirmed_animation_category_rows.py",
    "manual_confirmed_default": false,
    "instructions": [
      "Review each item, then set manual_confirmed=true only for rules whose keywords match the goods type.",
      "Save confirmed items to server/animation_category_name_split_confirmed_rows.json before running the import tool.",
      "Keep count checks enabled unless the catalog was regenerated after this report."
    ],
    "items": []
  },
  "automation_policy": {
    "auto_apply_category_changes": false,
    "auto_create_folders": false,
    "requires_manual_review": true,
    "manual_confirmation_template": "server/animation_category_name_split_confirmed_rows.template.json",
    "confirmed_queue": "server/animation_category_name_split_confirmed_rows.json",
    "import_tool": "tools/import_confirmed_animation_category_rows.py",
    "unblocks_when": "name_level_split_manually_confirmed",
    "reason": "Broad animation categories need name-level evidence before changing catalog categories or app folders."
  },
  "instructions": [
    "Review each name_level_split_template and set manual_confirmed=true only after checking real item names.",
    "Leave unmatched_sample_names in the source category until a safer keyword or official category is confirmed.",
    "Use candidate_priority_queue to confirm the largest name-level split rules first.",
    "Use price and release metadata from the existing catalog; this report only prepares category/folder changes.",
    "Folder colors remain grouped by color family so similar colors stay sorted together in the app."
  ]
}
