{
  "schema_version": 1,
  "generated_at": "2026-07-21T22:36:15Z",
  "scope": "catalog_image_attachment_action_queue",
  "summary": {
    "actionable_image_rows": 73,
    "queued_image_rows": 25,
    "action_batch_count": 4,
    "sample_action_item_rows": 25,
    "batch_size": 20,
    "max_batches": 18,
    "by_workflow": [
      [
        "replace_generic_source_then_extract_image",
        15
      ],
      [
        "review_gotouchi_official_candidates",
        10
      ]
    ],
    "by_source_store": [
      [
        "Stellive Store",
        10
      ],
      [
        "ご当地ちいかわ 공식(API)",
        10
      ],
      [
        "Weverse Shop",
        3
      ],
      [
        "포켓몬 센터",
        2
      ]
    ],
    "excluded_workflow_rows": [
      [
        "find_source_then_extract_image",
        642
      ],
      [
        "manual_image_research",
        5
      ]
    ],
    "auto_apply_enabled": false
  },
  "instructions": [
    "Use this queue for image-url work that is closer to actionable than broad source discovery.",
    "Every image still needs exact product evidence before catalog mutation.",
    "Rows without source_url stay in catalog_image_enrichment_batches_public.json and source discovery queues."
  ],
  "batches": [
    {
      "batch_id": "image-attachment-action-001",
      "priority": 20,
      "workflow": "replace_generic_source_then_extract_image",
      "source_store": "Stellive Store",
      "row_count": 10,
      "offset": 0,
      "review_state": "exact_product_image_confirmation_required",
      "next_machine_step": "replace_generic_source_url_then_extract_image",
      "recommended_action": "Replace generic storefront URL with exact product page before image import.",
      "category_counts": [
        [
          "인형",
          4
        ],
        [
          "액세서리",
          3
        ],
        [
          "아크릴 스탠드",
          2
        ],
        [
          "캔뱃지",
          1
        ]
      ],
      "items": [
        {
          "catalog_index": 2325,
          "workflow": "replace_generic_source_then_extract_image",
          "source_store": "Stellive Store",
          "name_ko": "스텔라이브 1주년 뱃지 세트",
          "name_ja": null,
          "series_name": null,
          "category": "캔뱃지",
          "source_url": "https://fanding.kr/@stellive/shop",
          "official_search_url": "https://stellive.fanding.kr/search?keyword=%EC%8A%A4%ED%85%94%EB%9D%BC%EC%9D%B4%EB%B8%8C%201%EC%A3%BC%EB%85%84%20%EB%B1%83%EC%A7%80%20%EC%84%B8%ED%8A%B8",
          "catalog_field_import_template": {
            "manual_confirmed": false,
            "manual_note": "",
            "row_index": 2325,
            "field": "image_url",
            "manual_value": "",
            "evidence_url": "",
            "candidate_source_url": "",
            "source_store": "Stellive Store",
            "name_ko": "스텔라이브 1주년 뱃지 세트",
            "name_ja": null,
            "category": "캔뱃지",
            "affiliation": "스텔라이브",
            "source_search_url": "https://stellive.fanding.kr/search?keyword=%EC%8A%A4%ED%85%94%EB%9D%BC%EC%9D%B4%EB%B8%8C%201%EC%A3%BC%EB%85%84%20%EB%B1%83%EC%A7%80%20%EC%84%B8%ED%8A%B8",
            "workflow": "replace_generic_source_then_extract_image",
            "requires_exact_source_url": true,
            "requires_representative_image_flag": false,
            "blocked_until": "exact_product_source_url_confirmed"
          },
          "review_state": "exact_product_image_confirmation_required",
          "auto_apply_enabled": false
        },
        {
          "catalog_index": 2352,
          "workflow": "replace_generic_source_then_extract_image",
          "source_store": "Stellive Store",
          "name_ko": "강지 마스코트 인형",
          "name_ja": null,
          "series_name": null,
          "category": "인형",
          "source_url": "https://fanding.kr/@stellive/shop",
          "official_search_url": "https://stellive.fanding.kr/search?keyword=%EA%B0%95%EC%A7%80%20%EB%A7%88%EC%8A%A4%EC%BD%94%ED%8A%B8%20%EC%9D%B8%ED%98%95",
          "catalog_field_import_template": {
            "manual_confirmed": false,
            "manual_note": "",
            "row_index": 2352,
            "field": "image_url",
            "manual_value": "",
            "evidence_url": "",
            "candidate_source_url": "",
            "source_store": "Stellive Store",
            "name_ko": "강지 마스코트 인형",
            "name_ja": null,
            "category": "인형",
            "affiliation": "스텔라이브",
            "source_search_url": "https://stellive.fanding.kr/search?keyword=%EA%B0%95%EC%A7%80%20%EB%A7%88%EC%8A%A4%EC%BD%94%ED%8A%B8%20%EC%9D%B8%ED%98%95",
            "workflow": "replace_generic_source_then_extract_image",
            "requires_exact_source_url": true,
            "requires_representative_image_flag": false,
            "blocked_until": "exact_product_source_url_confirmed"
          },
          "review_state": "exact_product_image_confirmation_required",
          "auto_apply_enabled": false
        },
        {
          "catalog_index": 2355,
          "workflow": "replace_generic_source_then_extract_image",
          "source_store": "Stellive Store",
          "name_ko": "아이리 칸나 생일 기념 굿즈 박스",
          "name_ja": null,
          "series_name": null,
          "category": "액세서리",
          "source_url": "https://fanding.kr/@stellive/shop",
          "official_search_url": "https://stellive.fanding.kr/search?keyword=%EC%95%84%EC%9D%B4%EB%A6%AC%20%EC%B9%B8%EB%82%98%20%EC%83%9D%EC%9D%BC%20%EA%B8%B0%EB%85%90%20%EA%B5%BF%EC%A6%88%20%EB%B0%95%EC%8A%A4",
          "catalog_field_import_template": {
            "manual_confirmed": false,
            "manual_note": "",
            "row_index": 2355,
            "field": "image_url",
            "manual_value": "",
            "evidence_url": "",
            "candidate_source_url": "",
            "source_store": "Stellive Store",
            "name_ko": "아이리 칸나 생일 기념 굿즈 박스",
            "name_ja": null,
            "category": "액세서리",
            "affiliation": "(전) 스텔라이브",
            "source_search_url": "https://stellive.fanding.kr/search?keyword=%EC%95%84%EC%9D%B4%EB%A6%AC%20%EC%B9%B8%EB%82%98%20%EC%83%9D%EC%9D%BC%20%EA%B8%B0%EB%85%90%20%EA%B5%BF%EC%A6%88%20%EB%B0%95%EC%8A%A4",
            "workflow": "replace_generic_source_then_extract_image",
            "requires_exact_source_url": true,
            "requires_representative_image_flag": false,
            "blocked_until": "exact_product_source_url_confirmed"
          },
          "review_state": "exact_product_image_confirmation_required",
          "auto_apply_enabled": false
        },
        {
          "catalog_index": 2356,
          "workflow": "replace_generic_source_then_extract_image",
          "source_store": "Stellive Store",
          "name_ko": "아이리 칸나 마스코트 인형",
          "name_ja": null,
          "series_name": null,
          "category": "인형",
          "source_url": "https://fanding.kr/@stellive/shop",
          "official_search_url": "https://stellive.fanding.kr/search?keyword=%EC%95%84%EC%9D%B4%EB%A6%AC%20%EC%B9%B8%EB%82%98%20%EB%A7%88%EC%8A%A4%EC%BD%94%ED%8A%B8%20%EC%9D%B8%ED%98%95",
          "catalog_field_import_template": {
            "manual_confirmed": false,
            "manual_note": "",
            "row_index": 2356,
            "field": "image_url",
            "manual_value": "",
            "evidence_url": "",
            "candidate_source_url": "",
            "source_store": "Stellive Store",
            "name_ko": "아이리 칸나 마스코트 인형",
            "name_ja": null,
            "category": "인형",
            "affiliation": "(전) 스텔라이브",
            "source_search_url": "https://stellive.fanding.kr/search?keyword=%EC%95%84%EC%9D%B4%EB%A6%AC%20%EC%B9%B8%EB%82%98%20%EB%A7%88%EC%8A%A4%EC%BD%94%ED%8A%B8%20%EC%9D%B8%ED%98%95",
            "workflow": "replace_generic_source_then_extract_image",
            "requires_exact_source_url": true,
            "requires_representative_image_flag": false,
            "blocked_until": "exact_product_source_url_confirmed"
          },
          "review_state": "exact_product_image_confirmation_required",
          "auto_apply_enabled": false
        },
        {
          "catalog_index": 2357,
          "workflow": "replace_generic_source_then_extract_image",
          "source_store": "Stellive Store",
          "name_ko": "아이리 칸나 키링 세트",
          "name_ja": null,
          "series_name": null,
          "category": "액세서리",
          "source_url": "https://fanding.kr/@stellive/shop",
          "official_search_url": "https://stellive.fanding.kr/search?keyword=%EC%95%84%EC%9D%B4%EB%A6%AC%20%EC%B9%B8%EB%82%98%20%ED%82%A4%EB%A7%81%20%EC%84%B8%ED%8A%B8",
          "catalog_field_import_template": {
            "manual_confirmed": false,
            "manual_note": "",
            "row_index": 2357,
            "field": "image_url",
            "manual_value": "",
            "evidence_url": "",
            "candidate_source_url": "",
            "source_store": "Stellive Store",
            "name_ko": "아이리 칸나 키링 세트",
            "name_ja": null,
            "category": "액세서리",
            "affiliation": "(전) 스텔라이브",
            "source_search_url": "https://stellive.fanding.kr/search?keyword=%EC%95%84%EC%9D%B4%EB%A6%AC%20%EC%B9%B8%EB%82%98%20%ED%82%A4%EB%A7%81%20%EC%84%B8%ED%8A%B8",
            "workflow": "replace_generic_source_then_extract_image",
            "requires_exact_source_url": true,
            "requires_representative_image_flag": false,
            "blocked_until": "exact_product_source_url_confirmed"
          },
          "review_state": "exact_product_image_confirmation_required",
          "auto_apply_enabled": false
        },
        {
          "catalog_index": 2361,
          "workflow": "replace_generic_source_then_extract_image",
          "source_store": "Stellive Store",
          "name_ko": "쿠루미 노아 데뷔 기념 아크릴 스탠드",
          "name_ja": null,
          "series_name": null,
          "category": "아크릴 스탠드",
          "source_url": "https://fanding.kr/@stellive/shop",
          "official_search_url": "https://stellive.fanding.kr/search?keyword=%EC%BF%A0%EB%A3%A8%EB%AF%B8%20%EB%85%B8%EC%95%84%20%EB%8D%B0%EB%B7%94%20%EA%B8%B0%EB%85%90%20%EC%95%84%ED%81%AC%EB%A6%B4%20%EC%8A%A4%ED%83%A0%EB%93%9C",
          "catalog_field_import_template": {
            "manual_confirmed": false,
            "manual_note": "",
            "row_index": 2361,
            "field": "image_url",
            "manual_value": "",
            "evidence_url": "",
            "candidate_source_url": "",
            "source_store": "Stellive Store",
            "name_ko": "쿠루미 노아 데뷔 기념 아크릴 스탠드",
            "name_ja": null,
            "category": "아크릴 스탠드",
            "affiliation": "스텔라이브",
            "source_search_url": "https://stellive.fanding.kr/search?keyword=%EC%BF%A0%EB%A3%A8%EB%AF%B8%20%EB%85%B8%EC%95%84%20%EB%8D%B0%EB%B7%94%20%EA%B8%B0%EB%85%90%20%EC%95%84%ED%81%AC%EB%A6%B4%20%EC%8A%A4%ED%83%A0%EB%93%9C",
            "workflow": "replace_generic_source_then_extract_image",
            "requires_exact_source_url": true,
            "requires_representative_image_flag": false,
            "blocked_until": "exact_product_source_url_confirmed"
          },
          "review_state": "exact_product_image_confirmation_required",
          "auto_apply_enabled": false
        },
        {
          "catalog_index": 2362,
          "workflow": "replace_generic_source_then_extract_image",
          "source_store": "Stellive Store",
          "name_ko": "쿠루미 노아 생일 기념 굿즈",
          "name_ja": null,
          "series_name": null,
          "category": "액세서리",
          "source_url": "https://fanding.kr/@stellive/shop",
          "official_search_url": "https://stellive.fanding.kr/search?keyword=%EC%BF%A0%EB%A3%A8%EB%AF%B8%20%EB%85%B8%EC%95%84%20%EC%83%9D%EC%9D%BC%20%EA%B8%B0%EB%85%90%20%EA%B5%BF%EC%A6%88",
          "catalog_field_import_template": {
            "manual_confirmed": false,
            "manual_note": "",
            "row_index": 2362,
            "field": "image_url",
            "manual_value": "",
            "evidence_url": "",
            "candidate_source_url": "",
            "source_store": "Stellive Store",
            "name_ko": "쿠루미 노아 생일 기념 굿즈",
            "name_ja": null,
            "category": "액세서리",
            "affiliation": "스텔라이브",
            "source_search_url": "https://stellive.fanding.kr/search?keyword=%EC%BF%A0%EB%A3%A8%EB%AF%B8%20%EB%85%B8%EC%95%84%20%EC%83%9D%EC%9D%BC%20%EA%B8%B0%EB%85%90%20%EA%B5%BF%EC%A6%88",
            "workflow": "replace_generic_source_then_extract_image",
            "requires_exact_source_url": true,
            "requires_representative_image_flag": false,
            "blocked_until": "exact_product_source_url_confirmed"
          },
          "review_state": "exact_product_image_confirmation_required",
          "auto_apply_enabled": false
        },
        {
          "catalog_index": 2363,
          "workflow": "replace_generic_source_then_extract_image",
          "source_store": "Stellive Store",
          "name_ko": "쿠루미 노아 마스코트 인형",
          "name_ja": null,
          "series_name": null,
          "category": "인형",
          "source_url": "https://fanding.kr/@stellive/shop",
          "official_search_url": "https://stellive.fanding.kr/search?keyword=%EC%BF%A0%EB%A3%A8%EB%AF%B8%20%EB%85%B8%EC%95%84%20%EB%A7%88%EC%8A%A4%EC%BD%94%ED%8A%B8%20%EC%9D%B8%ED%98%95",
          "catalog_field_import_template": {
            "manual_confirmed": false,
            "manual_note": "",
            "row_index": 2363,
            "field": "image_url",
            "manual_value": "",
            "evidence_url": "",
            "candidate_source_url": "",
            "source_store": "Stellive Store",
            "name_ko": "쿠루미 노아 마스코트 인형",
            "name_ja": null,
            "category": "인형",
            "affiliation": "스텔라이브",
            "source_search_url": "https://stellive.fanding.kr/search?keyword=%EC%BF%A0%EB%A3%A8%EB%AF%B8%20%EB%85%B8%EC%95%84%20%EB%A7%88%EC%8A%A4%EC%BD%94%ED%8A%B8%20%EC%9D%B8%ED%98%95",
            "workflow": "replace_generic_source_then_extract_image",
            "requires_exact_source_url": true,
            "requires_representative_image_flag": false,
            "blocked_until": "exact_product_source_url_confirmed"
          },
          "review_state": "exact_product_image_confirmation_required",
          "auto_apply_enabled": false
        },
        {
          "catalog_index": 2372,
          "workflow": "replace_generic_source_then_extract_image",
          "source_store": "Stellive Store",
          "name_ko": "하나코 코코나 마스코트 인형",
          "name_ja": null,
          "series_name": null,
          "category": "인형",
          "source_url": "https://fanding.kr/@stellive/shop",
          "official_search_url": "https://stellive.fanding.kr/search?keyword=%ED%95%98%EB%82%98%EC%BD%94%20%EC%BD%94%EC%BD%94%EB%82%98%20%EB%A7%88%EC%8A%A4%EC%BD%94%ED%8A%B8%20%EC%9D%B8%ED%98%95",
          "catalog_field_import_template": {
            "manual_confirmed": false,
            "manual_note": "",
            "row_index": 2372,
            "field": "image_url",
            "manual_value": "",
            "evidence_url": "",
            "candidate_source_url": "",
            "source_store": "Stellive Store",
            "name_ko": "하나코 코코나 마스코트 인형",
            "name_ja": null,
            "category": "인형",
            "affiliation": "스텔라이브",
            "source_search_url": "https://stellive.fanding.kr/search?keyword=%ED%95%98%EB%82%98%EC%BD%94%20%EC%BD%94%EC%BD%94%EB%82%98%20%EB%A7%88%EC%8A%A4%EC%BD%94%ED%8A%B8%20%EC%9D%B8%ED%98%95",
            "workflow": "replace_generic_source_then_extract_image",
            "requires_exact_source_url": true,
            "requires_representative_image_flag": false,
            "blocked_until": "exact_product_source_url_confirmed"
          },
          "review_state": "exact_product_image_confirmation_required",
          "auto_apply_enabled": false
        },
        {
          "catalog_index": 2373,
          "workflow": "replace_generic_source_then_extract_image",
          "source_store": "Stellive Store",
          "name_ko": "비비 데뷔 기념 아크릴 스탠드",
          "name_ja": null,
          "series_name": null,
          "category": "아크릴 스탠드",
          "source_url": "https://fanding.kr/@stellive/shop",
          "official_search_url": "https://stellive.fanding.kr/search?keyword=%EB%B9%84%EB%B9%84%20%EB%8D%B0%EB%B7%94%20%EA%B8%B0%EB%85%90%20%EC%95%84%ED%81%AC%EB%A6%B4%20%EC%8A%A4%ED%83%A0%EB%93%9C",
          "catalog_field_import_template": {
            "manual_confirmed": false,
            "manual_note": "",
            "row_index": 2373,
            "field": "image_url",
            "manual_value": "",
            "evidence_url": "",
            "candidate_source_url": "",
            "source_store": "Stellive Store",
            "name_ko": "비비 데뷔 기념 아크릴 스탠드",
            "name_ja": null,
            "category": "아크릴 스탠드",
            "affiliation": "스텔라이브",
            "source_search_url": "https://stellive.fanding.kr/search?keyword=%EB%B9%84%EB%B9%84%20%EB%8D%B0%EB%B7%94%20%EA%B8%B0%EB%85%90%20%EC%95%84%ED%81%AC%EB%A6%B4%20%EC%8A%A4%ED%83%A0%EB%93%9C",
            "workflow": "replace_generic_source_then_extract_image",
            "requires_exact_source_url": true,
            "requires_representative_image_flag": false,
            "blocked_until": "exact_product_source_url_confirmed"
          },
          "review_state": "exact_product_image_confirmation_required",
          "auto_apply_enabled": false
        }
      ],
      "auto_apply_enabled": false
    },
    {
      "batch_id": "image-attachment-action-002",
      "priority": 20,
      "workflow": "replace_generic_source_then_extract_image",
      "source_store": "Weverse Shop",
      "row_count": 3,
      "offset": 0,
      "review_state": "exact_product_image_confirmation_required",
      "next_machine_step": "replace_generic_source_url_then_extract_image",
      "recommended_action": "Replace generic storefront URL with exact product page before image import.",
      "category_counts": [
        [
          "포토카드",
          3
        ]
      ],
      "items": [
        {
          "catalog_index": 17613,
          "workflow": "replace_generic_source_then_extract_image",
          "source_store": "Weverse Shop",
          "name_ko": "SEVENTEEN 포토카드 (랜덤)",
          "name_ja": null,
          "series_name": null,
          "category": "포토카드",
          "source_url": "https://shop.weverse.io/home",
          "official_search_url": null,
          "catalog_field_import_template": {
            "manual_confirmed": false,
            "manual_note": "",
            "row_index": 17613,
            "field": "image_url",
            "manual_value": "",
            "evidence_url": "",
            "candidate_source_url": "",
            "source_store": "Weverse Shop",
            "name_ko": "SEVENTEEN 포토카드 (랜덤)",
            "name_ja": null,
            "category": "포토카드",
            "affiliation": "SEVENTEEN",
            "source_search_url": null,
            "workflow": "replace_generic_source_then_extract_image",
            "requires_exact_source_url": true,
            "requires_representative_image_flag": false,
            "blocked_until": "exact_product_source_url_confirmed"
          },
          "review_state": "exact_product_image_confirmation_required",
          "auto_apply_enabled": false
        },
        {
          "catalog_index": 17622,
          "workflow": "replace_generic_source_then_extract_image",
          "source_store": "Weverse Shop",
          "name_ko": "ZEROBASEONE 포토카드 (랜덤)",
          "name_ja": null,
          "series_name": null,
          "category": "포토카드",
          "source_url": "https://shop.weverse.io/home",
          "official_search_url": null,
          "catalog_field_import_template": {
            "manual_confirmed": false,
            "manual_note": "",
            "row_index": 17622,
            "field": "image_url",
            "manual_value": "",
            "evidence_url": "",
            "candidate_source_url": "",
            "source_store": "Weverse Shop",
            "name_ko": "ZEROBASEONE 포토카드 (랜덤)",
            "name_ja": null,
            "category": "포토카드",
            "affiliation": "ZEROBASEONE",
            "source_search_url": null,
            "workflow": "replace_generic_source_then_extract_image",
            "requires_exact_source_url": true,
            "requires_representative_image_flag": false,
            "blocked_until": "exact_product_source_url_confirmed"
          },
          "review_state": "exact_product_image_confirmation_required",
          "auto_apply_enabled": false
        },
        {
          "catalog_index": 17623,
          "workflow": "replace_generic_source_then_extract_image",
          "source_store": "Weverse Shop",
          "name_ko": "ILLIT 포토카드 (랜덤)",
          "name_ja": null,
          "series_name": null,
          "category": "포토카드",
          "source_url": "https://shop.weverse.io/home",
          "official_search_url": null,
          "catalog_field_import_template": {
            "manual_confirmed": false,
            "manual_note": "",
            "row_index": 17623,
            "field": "image_url",
            "manual_value": "",
            "evidence_url": "",
            "candidate_source_url": "",
            "source_store": "Weverse Shop",
            "name_ko": "ILLIT 포토카드 (랜덤)",
            "name_ja": null,
            "category": "포토카드",
            "affiliation": "ILLIT",
            "source_search_url": null,
            "workflow": "replace_generic_source_then_extract_image",
            "requires_exact_source_url": true,
            "requires_representative_image_flag": false,
            "blocked_until": "exact_product_source_url_confirmed"
          },
          "review_state": "exact_product_image_confirmation_required",
          "auto_apply_enabled": false
        }
      ],
      "auto_apply_enabled": false
    },
    {
      "batch_id": "image-attachment-action-003",
      "priority": 20,
      "workflow": "replace_generic_source_then_extract_image",
      "source_store": "포켓몬 센터",
      "row_count": 2,
      "offset": 0,
      "review_state": "exact_product_image_confirmation_required",
      "next_machine_step": "replace_generic_source_url_then_extract_image",
      "recommended_action": "Replace generic storefront URL with exact product page before image import.",
      "category_counts": [
        [
          "인형",
          1
        ],
        [
          "트레이딩 카드",
          1
        ]
      ],
      "items": [
        {
          "catalog_index": 1098,
          "workflow": "replace_generic_source_then_extract_image",
          "source_store": "포켓몬 센터",
          "name_ko": "포켓몬 봉제 인형 (피카츄)",
          "name_ja": "ポケモン ぬいぐるみ (ピカチュウ)",
          "series_name": null,
          "category": "인형",
          "source_url": "https://www.pokemoncenter-online.com/",
          "official_search_url": null,
          "catalog_field_import_template": {
            "manual_confirmed": false,
            "manual_note": "",
            "row_index": 1098,
            "field": "image_url",
            "manual_value": "",
            "evidence_url": "",
            "candidate_source_url": "",
            "source_store": "포켓몬 센터",
            "name_ko": "포켓몬 봉제 인형 (피카츄)",
            "name_ja": "ポケモン ぬいぐるみ (ピカチュウ)",
            "category": "인형",
            "affiliation": "포켓몬",
            "source_search_url": null,
            "workflow": "replace_generic_source_then_extract_image",
            "requires_exact_source_url": true,
            "requires_representative_image_flag": false,
            "blocked_until": "exact_product_source_url_confirmed"
          },
          "review_state": "exact_product_image_confirmation_required",
          "auto_apply_enabled": false
        },
        {
          "catalog_index": 17593,
          "workflow": "replace_generic_source_then_extract_image",
          "source_store": "포켓몬 센터",
          "name_ko": "포켓몬 카드 게임 부스터 팩",
          "name_ja": null,
          "series_name": null,
          "category": "트레이딩 카드",
          "source_url": "https://www.pokemoncenter-online.com/",
          "official_search_url": null,
          "catalog_field_import_template": {
            "manual_confirmed": false,
            "manual_note": "",
            "row_index": 17593,
            "field": "image_url",
            "manual_value": "",
            "evidence_url": "",
            "candidate_source_url": "",
            "source_store": "포켓몬 센터",
            "name_ko": "포켓몬 카드 게임 부스터 팩",
            "name_ja": null,
            "category": "트레이딩 카드",
            "affiliation": "포켓몬",
            "source_search_url": null,
            "workflow": "replace_generic_source_then_extract_image",
            "requires_exact_source_url": true,
            "requires_representative_image_flag": false,
            "blocked_until": "exact_product_source_url_confirmed"
          },
          "review_state": "exact_product_image_confirmation_required",
          "auto_apply_enabled": false
        }
      ],
      "auto_apply_enabled": false
    },
    {
      "batch_id": "image-attachment-action-004",
      "priority": 30,
      "workflow": "review_gotouchi_official_candidates",
      "source_store": "ご当地ちいかわ 공식(API)",
      "row_count": 10,
      "offset": 0,
      "review_state": "exact_product_image_confirmation_required",
      "next_machine_step": "confirm_exact_gotouchi_product_type_then_attach_image",
      "recommended_action": "Confirm motif candidate matches product type before image import.",
      "category_counts": [
        [
          "마스코트",
          4
        ],
        [
          "아크릴 키링",
          3
        ],
        [
          "타월",
          3
        ]
      ],
      "items": [
        {
          "catalog_index": 936,
          "workflow": "review_gotouchi_official_candidates",
          "source_store": "ご当地ちいかわ 공식(API)",
          "name_ko": "치이카와 ご当地 아크릴 키홀더 (아사쿠사 카미나리몬)",
          "name_ja": "ちいかわ ご当地アクリルキーホルダー (浅草 雷門)",
          "series_name": "ご当地",
          "category": "아크릴 키링",
          "source_url": "https://www.jp-api.com/contents/NOD62/",
          "official_search_url": null,
          "catalog_field_import_template": {
            "manual_confirmed": false,
            "manual_note": "",
            "row_index": 936,
            "field": "image_url",
            "manual_value": "",
            "evidence_url": "",
            "candidate_source_url": "",
            "source_store": "ご当地ちいかわ 공식(API)",
            "name_ko": "치이카와 ご当地 아크릴 키홀더 (아사쿠사 카미나리몬)",
            "name_ja": "ちいかわ ご当地アクリルキーホルダー (浅草 雷門)",
            "category": "아크릴 키링",
            "affiliation": "치이카와",
            "source_search_url": null,
            "workflow": "review_gotouchi_official_candidates",
            "requires_exact_source_url": true,
            "requires_representative_image_flag": true,
            "blocked_until": "exact_product_source_url_confirmed"
          },
          "review_state": "exact_product_image_confirmation_required",
          "auto_apply_enabled": false
        },
        {
          "catalog_index": 937,
          "workflow": "review_gotouchi_official_candidates",
          "source_store": "ご当地ちいかわ 공식(API)",
          "name_ko": "우사기 ご当地 마스코트 (아사쿠사 깃발)",
          "name_ja": "うさぎ ご当地マスコット (浅草)",
          "series_name": "ご当地",
          "category": "마스코트",
          "source_url": "https://www.jp-api.com/contents/NOD62/",
          "official_search_url": null,
          "catalog_field_import_template": {
            "manual_confirmed": false,
            "manual_note": "",
            "row_index": 937,
            "field": "image_url",
            "manual_value": "",
            "evidence_url": "",
            "candidate_source_url": "",
            "source_store": "ご当地ちいかわ 공식(API)",
            "name_ko": "우사기 ご当地 마스코트 (아사쿠사 깃발)",
            "name_ja": "うさぎ ご当地マスコット (浅草)",
            "category": "마스코트",
            "affiliation": "치이카와",
            "source_search_url": null,
            "workflow": "review_gotouchi_official_candidates",
            "requires_exact_source_url": true,
            "requires_representative_image_flag": true,
            "blocked_until": "exact_product_source_url_confirmed"
          },
          "review_state": "exact_product_image_confirmation_required",
          "auto_apply_enabled": false
        },
        {
          "catalog_index": 938,
          "workflow": "review_gotouchi_official_candidates",
          "source_store": "ご当地ちいかわ 공식(API)",
          "name_ko": "치이카와 ご当地 미니 타올 (도쿄)",
          "name_ja": "ちいかわ ご当地ミニタオル (東京)",
          "series_name": "ご当地",
          "category": "타월",
          "source_url": "https://www.jp-api.com/contents/NOD62/",
          "official_search_url": null,
          "catalog_field_import_template": {
            "manual_confirmed": false,
            "manual_note": "",
            "row_index": 938,
            "field": "image_url",
            "manual_value": "",
            "evidence_url": "",
            "candidate_source_url": "",
            "source_store": "ご当地ちいかわ 공식(API)",
            "name_ko": "치이카와 ご当地 미니 타올 (도쿄)",
            "name_ja": "ちいかわ ご当地ミニタオル (東京)",
            "category": "타월",
            "affiliation": "치이카와",
            "source_search_url": null,
            "workflow": "review_gotouchi_official_candidates",
            "requires_exact_source_url": true,
            "requires_representative_image_flag": true,
            "blocked_until": "exact_product_source_url_confirmed"
          },
          "review_state": "exact_product_image_confirmation_required",
          "auto_apply_enabled": false
        },
        {
          "catalog_index": 941,
          "workflow": "review_gotouchi_official_candidates",
          "source_store": "ご当地ちいかわ 공식(API)",
          "name_ko": "우사기 ご当地 마스코트 (오사카 통천각)",
          "name_ja": "うさぎ ご当地マスコット (大阪 通天閣)",
          "series_name": "ご当地",
          "category": "마스코트",
          "source_url": "https://www.jp-api.com/contents/NOD62/",
          "official_search_url": null,
          "catalog_field_import_template": {
            "manual_confirmed": false,
            "manual_note": "",
            "row_index": 941,
            "field": "image_url",
            "manual_value": "",
            "evidence_url": "",
            "candidate_source_url": "",
            "source_store": "ご当地ちいかわ 공식(API)",
            "name_ko": "우사기 ご当地 마스코트 (오사카 통천각)",
            "name_ja": "うさぎ ご当地マスコット (大阪 通天閣)",
            "category": "마스코트",
            "affiliation": "치이카와",
            "source_search_url": null,
            "workflow": "review_gotouchi_official_candidates",
            "requires_exact_source_url": true,
            "requires_representative_image_flag": true,
            "blocked_until": "exact_product_source_url_confirmed"
          },
          "review_state": "exact_product_image_confirmation_required",
          "auto_apply_enabled": false
        },
        {
          "catalog_index": 942,
          "workflow": "review_gotouchi_official_candidates",
          "source_store": "ご当地ちいかわ 공식(API)",
          "name_ko": "치이카와 ご当地 아크릴 키홀더 (오사카 타코야키)",
          "name_ja": "ちいかわ ご当地アクリルキーホルダー (大阪 たこ焼き)",
          "series_name": "ご当地",
          "category": "아크릴 키링",
          "source_url": "https://www.jp-api.com/contents/NOD62/",
          "official_search_url": null,
          "catalog_field_import_template": {
            "manual_confirmed": false,
            "manual_note": "",
            "row_index": 942,
            "field": "image_url",
            "manual_value": "",
            "evidence_url": "",
            "candidate_source_url": "",
            "source_store": "ご当地ちいかわ 공식(API)",
            "name_ko": "치이카와 ご当地 아크릴 키홀더 (오사카 타코야키)",
            "name_ja": "ちいかわ ご当地アクリルキーホルダー (大阪 たこ焼き)",
            "category": "아크릴 키링",
            "affiliation": "치이카와",
            "source_search_url": null,
            "workflow": "review_gotouchi_official_candidates",
            "requires_exact_source_url": true,
            "requires_representative_image_flag": true,
            "blocked_until": "exact_product_source_url_confirmed"
          },
          "review_state": "exact_product_image_confirmation_required",
          "auto_apply_enabled": false
        },
        {
          "catalog_index": 943,
          "workflow": "review_gotouchi_official_candidates",
          "source_store": "ご当地ちいかわ 공식(API)",
          "name_ko": "치이카와 ご当地 미니 타올 (오사카)",
          "name_ja": "ちいかわ ご当地ミニタオル (大阪)",
          "series_name": "ご当地",
          "category": "타월",
          "source_url": "https://www.jp-api.com/contents/NOD62/",
          "official_search_url": null,
          "catalog_field_import_template": {
            "manual_confirmed": false,
            "manual_note": "",
            "row_index": 943,
            "field": "image_url",
            "manual_value": "",
            "evidence_url": "",
            "candidate_source_url": "",
            "source_store": "ご当地ちいかわ 공식(API)",
            "name_ko": "치이카와 ご当地 미니 타올 (오사카)",
            "name_ja": "ちいかわ ご当地ミニタオル (大阪)",
            "category": "타월",
            "affiliation": "치이카와",
            "source_search_url": null,
            "workflow": "review_gotouchi_official_candidates",
            "requires_exact_source_url": true,
            "requires_representative_image_flag": true,
            "blocked_until": "exact_product_source_url_confirmed"
          },
          "review_state": "exact_product_image_confirmation_required",
          "auto_apply_enabled": false
        },
        {
          "catalog_index": 944,
          "workflow": "review_gotouchi_official_candidates",
          "source_store": "ご当地ちいかわ 공식(API)",
          "name_ko": "치이카와 ご当地 마스코트 (교토 마이코)",
          "name_ja": "ちいかわ ご当地マスコット (京都 舞妓)",
          "series_name": "ご当地",
          "category": "마스코트",
          "source_url": "https://www.jp-api.com/contents/NOD62/",
          "official_search_url": null,
          "catalog_field_import_template": {
            "manual_confirmed": false,
            "manual_note": "",
            "row_index": 944,
            "field": "image_url",
            "manual_value": "",
            "evidence_url": "",
            "candidate_source_url": "",
            "source_store": "ご当地ちいかわ 공식(API)",
            "name_ko": "치이카와 ご当地 마스코트 (교토 마이코)",
            "name_ja": "ちいかわ ご当地マスコット (京都 舞妓)",
            "category": "마스코트",
            "affiliation": "치이카와",
            "source_search_url": null,
            "workflow": "review_gotouchi_official_candidates",
            "requires_exact_source_url": true,
            "requires_representative_image_flag": true,
            "blocked_until": "exact_product_source_url_confirmed"
          },
          "review_state": "exact_product_image_confirmation_required",
          "auto_apply_enabled": false
        },
        {
          "catalog_index": 945,
          "workflow": "review_gotouchi_official_candidates",
          "source_store": "ご当地ちいかわ 공식(API)",
          "name_ko": "하치와레 ご当地 마스코트 (교토 마이코)",
          "name_ja": "ハチワレ ご当地マスコット (京都 舞妓)",
          "series_name": "ご当地",
          "category": "마스코트",
          "source_url": "https://www.jp-api.com/contents/NOD62/",
          "official_search_url": null,
          "catalog_field_import_template": {
            "manual_confirmed": false,
            "manual_note": "",
            "row_index": 945,
            "field": "image_url",
            "manual_value": "",
            "evidence_url": "",
            "candidate_source_url": "",
            "source_store": "ご当地ちいかわ 공식(API)",
            "name_ko": "하치와레 ご当地 마스코트 (교토 마이코)",
            "name_ja": "ハチワレ ご当地マスコット (京都 舞妓)",
            "category": "마스코트",
            "affiliation": "치이카와",
            "source_search_url": null,
            "workflow": "review_gotouchi_official_candidates",
            "requires_exact_source_url": true,
            "requires_representative_image_flag": true,
            "blocked_until": "exact_product_source_url_confirmed"
          },
          "review_state": "exact_product_image_confirmation_required",
          "auto_apply_enabled": false
        },
        {
          "catalog_index": 946,
          "workflow": "review_gotouchi_official_candidates",
          "source_store": "ご当地ちいかわ 공식(API)",
          "name_ko": "우사기 ご当地 아크릴 키홀더 (교토 키요미즈데라)",
          "name_ja": "うさぎ ご当地アクリルキーホルダー (京都 清水寺)",
          "series_name": "ご当地",
          "category": "아크릴 키링",
          "source_url": "https://www.jp-api.com/contents/NOD62/",
          "official_search_url": null,
          "catalog_field_import_template": {
            "manual_confirmed": false,
            "manual_note": "",
            "row_index": 946,
            "field": "image_url",
            "manual_value": "",
            "evidence_url": "",
            "candidate_source_url": "",
            "source_store": "ご当地ちいかわ 공식(API)",
            "name_ko": "우사기 ご当地 아크릴 키홀더 (교토 키요미즈데라)",
            "name_ja": "うさぎ ご当地アクリルキーホルダー (京都 清水寺)",
            "category": "아크릴 키링",
            "affiliation": "치이카와",
            "source_search_url": null,
            "workflow": "review_gotouchi_official_candidates",
            "requires_exact_source_url": true,
            "requires_representative_image_flag": true,
            "blocked_until": "exact_product_source_url_confirmed"
          },
          "review_state": "exact_product_image_confirmation_required",
          "auto_apply_enabled": false
        },
        {
          "catalog_index": 950,
          "workflow": "review_gotouchi_official_candidates",
          "source_store": "ご当地ちいかわ 공식(API)",
          "name_ko": "치이카와 ご当地 미니 타올 (홋카이도)",
          "name_ja": "ちいかわ ご当地ミニタオル (北海道)",
          "series_name": "ご当地",
          "category": "타월",
          "source_url": "https://www.jp-api.com/contents/NOD62/",
          "official_search_url": null,
          "catalog_field_import_template": {
            "manual_confirmed": false,
            "manual_note": "",
            "row_index": 950,
            "field": "image_url",
            "manual_value": "",
            "evidence_url": "",
            "candidate_source_url": "",
            "source_store": "ご当地ちいかわ 공식(API)",
            "name_ko": "치이카와 ご当地 미니 타올 (홋카이도)",
            "name_ja": "ちいかわ ご当地ミニタオル (北海道)",
            "category": "타월",
            "affiliation": "치이카와",
            "source_search_url": null,
            "workflow": "review_gotouchi_official_candidates",
            "requires_exact_source_url": true,
            "requires_representative_image_flag": true,
            "blocked_until": "exact_product_source_url_confirmed"
          },
          "review_state": "exact_product_image_confirmation_required",
          "auto_apply_enabled": false
        }
      ],
      "auto_apply_enabled": false
    }
  ],
  "automation_policy": {
    "auto_apply_catalog_changes": false,
    "requires_manual_review": true,
    "private_collection_storage": "local_device_only"
  }
}
