{
  "schema_version": 1,
  "generated_at": "2026-07-22T08:08:09Z",
  "scope": "goodsmile_missing_image_search",
  "summary": {
    "missing_goodsmile_image_rows": 57,
    "queue_rows": 57,
    "matched_queue_rows": 57,
    "missing_queue_rows": 0,
    "missing_search_url_rows": 0,
    "official_search_url_rows": 57,
    "auto_apply_enabled": false,
    "search_page": "https://www.goodsmile.info/ja/products/search?utf8=%E2%9C%93&search%5Bquery%5D={query}"
  },
  "breakdowns": {
    "by_strategy": [
      {
        "strategy": "official_search",
        "rows": 57
      }
    ],
    "by_automation_safety": [
      {
        "automation_safety": "candidate_provider_script_required",
        "rows": 57
      }
    ],
    "by_category": [
      {
        "category": "피규어",
        "rows": 29
      },
      {
        "category": "아크릴 스탠드",
        "rows": 11
      },
      {
        "category": "캔뱃지",
        "rows": 6
      },
      {
        "category": "문구",
        "rows": 2
      },
      {
        "category": "머그컵",
        "rows": 2
      },
      {
        "category": "응원봉",
        "rows": 2
      },
      {
        "category": "키링",
        "rows": 1
      },
      {
        "category": "타월",
        "rows": 1
      },
      {
        "category": "가방",
        "rows": 1
      },
      {
        "category": "응원용품",
        "rows": 1
      },
      {
        "category": "생활잡화",
        "rows": 1
      }
    ],
    "by_affiliation": [
      {
        "affiliation": "하츠네 미쿠",
        "rows": 24
      },
      {
        "affiliation": "원피스",
        "rows": 7
      },
      {
        "affiliation": "메이드 인 어비스",
        "rows": 6
      },
      {
        "affiliation": "블루록",
        "rows": 4
      },
      {
        "affiliation": "단간론파",
        "rows": 3
      },
      {
        "affiliation": "장송의 프리렌",
        "rows": 3
      },
      {
        "affiliation": "봇치 더 록",
        "rows": 2
      },
      {
        "affiliation": "주술회전",
        "rows": 2
      },
      {
        "affiliation": "전생슬",
        "rows": 2
      },
      {
        "affiliation": "체인소 맨",
        "rows": 1
      },
      {
        "affiliation": "진격의 거인",
        "rows": 1
      },
      {
        "affiliation": "최애의 아이",
        "rows": 1
      },
      {
        "affiliation": "리제로",
        "rows": 1
      }
    ]
  },
  "items": [
    {
      "catalog_index": 1408,
      "name_ko": "POP UP PARADE 리코",
      "name_ja": "POP UP PARADE リコ",
      "affiliation": "메이드 인 어비스",
      "category": "피규어",
      "query": "POP UP PARADE リコ",
      "search_url": "https://www.goodsmile.info/ja/products/search?utf8=%E2%9C%93&search%5Bquery%5D=POP%20UP%20PARADE%20%E3%83%AA%E3%82%B3",
      "strategy": "official_search",
      "automation_safety": "candidate_provider_script_required",
      "manual_review_required": true,
      "import_template": {
        "catalog_index": 1408,
        "source_url": null,
        "image_url": null,
        "manual_confirmed": false,
        "blocked_until": "exact_goodsmile_product_page_confirmed"
      }
    },
    {
      "catalog_index": 1409,
      "name_ko": "POP UP PARADE 레그",
      "name_ja": "POP UP PARADE レグ",
      "affiliation": "메이드 인 어비스",
      "category": "피규어",
      "query": "POP UP PARADE レグ",
      "search_url": "https://www.goodsmile.info/ja/products/search?utf8=%E2%9C%93&search%5Bquery%5D=POP%20UP%20PARADE%20%E3%83%AC%E3%82%B0",
      "strategy": "official_search",
      "automation_safety": "candidate_provider_script_required",
      "manual_review_required": true,
      "import_template": {
        "catalog_index": 1409,
        "source_url": null,
        "image_url": null,
        "manual_confirmed": false,
        "blocked_until": "exact_goodsmile_product_page_confirmed"
      }
    },
    {
      "catalog_index": 1447,
      "name_ko": "넨도로이드 토가미 뱌쿠야",
      "name_ja": "ねんどろいど 十神白夜",
      "affiliation": "단간론파",
      "category": "피규어",
      "query": "ねんどろいど 十神白夜",
      "search_url": "https://www.goodsmile.info/ja/products/search?utf8=%E2%9C%93&search%5Bquery%5D=%E3%81%AD%E3%82%93%E3%81%A9%E3%82%8D%E3%81%84%E3%81%A9%20%E5%8D%81%E7%A5%9E%E7%99%BD%E5%A4%9C",
      "strategy": "official_search",
      "automation_safety": "candidate_provider_script_required",
      "manual_review_required": true,
      "import_template": {
        "catalog_index": 1447,
        "source_url": null,
        "image_url": null,
        "manual_confirmed": false,
        "blocked_until": "exact_goodsmile_product_page_confirmed"
      }
    },
    {
      "catalog_index": 1454,
      "name_ko": "넨도로이드 모모타 카이토",
      "name_ja": "ねんどろいど 百田解斗",
      "affiliation": "단간론파",
      "category": "피규어",
      "query": "ねんどろいど 百田解斗",
      "search_url": "https://www.goodsmile.info/ja/products/search?utf8=%E2%9C%93&search%5Bquery%5D=%E3%81%AD%E3%82%93%E3%81%A9%E3%82%8D%E3%81%84%E3%81%A9%20%E7%99%BE%E7%94%B0%E8%A7%A3%E6%96%97",
      "strategy": "official_search",
      "automation_safety": "candidate_provider_script_required",
      "manual_review_required": true,
      "import_template": {
        "catalog_index": 1454,
        "source_url": null,
        "image_url": null,
        "manual_confirmed": false,
        "blocked_until": "exact_goodsmile_product_page_confirmed"
      }
    },
    {
      "catalog_index": 1455,
      "name_ko": "POP UP PARADE 모노쿠마",
      "name_ja": "POP UP PARADE モノクマ",
      "affiliation": "단간론파",
      "category": "피규어",
      "query": "POP UP PARADE モノクマ",
      "search_url": "https://www.goodsmile.info/ja/products/search?utf8=%E2%9C%93&search%5Bquery%5D=POP%20UP%20PARADE%20%E3%83%A2%E3%83%8E%E3%82%AF%E3%83%9E",
      "strategy": "official_search",
      "automation_safety": "candidate_provider_script_required",
      "manual_review_required": true,
      "import_template": {
        "catalog_index": 1455,
        "source_url": null,
        "image_url": null,
        "manual_confirmed": false,
        "blocked_until": "exact_goodsmile_product_page_confirmed"
      }
    },
    {
      "catalog_index": 1485,
      "name_ko": "넨도로이드 아이젠",
      "name_ja": "ねんどろいど アイゼン",
      "affiliation": "장송의 프리렌",
      "category": "피규어",
      "query": "ねんどろいど アイゼン",
      "search_url": "https://www.goodsmile.info/ja/products/search?utf8=%E2%9C%93&search%5Bquery%5D=%E3%81%AD%E3%82%93%E3%81%A9%E3%82%8D%E3%81%84%E3%81%A9%20%E3%82%A2%E3%82%A4%E3%82%BC%E3%83%B3",
      "strategy": "official_search",
      "automation_safety": "candidate_provider_script_required",
      "manual_review_required": true,
      "import_template": {
        "catalog_index": 1485,
        "source_url": null,
        "image_url": null,
        "manual_confirmed": false,
        "blocked_until": "exact_goodsmile_product_page_confirmed"
      }
    },
    {
      "catalog_index": 1486,
      "name_ko": "넨도로이드 하이터",
      "name_ja": "ねんどろいど ハイター",
      "affiliation": "장송의 프리렌",
      "category": "피규어",
      "query": "ねんどろいど ハイター",
      "search_url": "https://www.goodsmile.info/ja/products/search?utf8=%E2%9C%93&search%5Bquery%5D=%E3%81%AD%E3%82%93%E3%81%A9%E3%82%8D%E3%81%84%E3%81%A9%20%E3%83%8F%E3%82%A4%E3%82%BF%E3%83%BC",
      "strategy": "official_search",
      "automation_safety": "candidate_provider_script_required",
      "manual_review_required": true,
      "import_template": {
        "catalog_index": 1486,
        "source_url": null,
        "image_url": null,
        "manual_confirmed": false,
        "blocked_until": "exact_goodsmile_product_page_confirmed"
      }
    },
    {
      "catalog_index": 1489,
      "name_ko": "POP UP PARADE 슈타르크",
      "name_ja": "POP UP PARADE シュタルク",
      "affiliation": "장송의 프리렌",
      "category": "피규어",
      "query": "POP UP PARADE シュタルク",
      "search_url": "https://www.goodsmile.info/ja/products/search?utf8=%E2%9C%93&search%5Bquery%5D=POP%20UP%20PARADE%20%E3%82%B7%E3%83%A5%E3%82%BF%E3%83%AB%E3%82%AF",
      "strategy": "official_search",
      "automation_safety": "candidate_provider_script_required",
      "manual_review_required": true,
      "import_template": {
        "catalog_index": 1489,
        "source_url": null,
        "image_url": null,
        "manual_confirmed": false,
        "blocked_until": "exact_goodsmile_product_page_confirmed"
      }
    },
    {
      "catalog_index": 1530,
      "name_ko": "하츠네 미쿠 러버 스트랩 (매지컬 미라이 2023)",
      "name_ja": "初音ミク ラバーストラップ (マジカルミライ2023)",
      "affiliation": "하츠네 미쿠",
      "category": "키링",
      "query": "初音ミク ラバーストラップ (マジカルミライ2023)",
      "search_url": "https://www.goodsmile.info/ja/products/search?utf8=%E2%9C%93&search%5Bquery%5D=%E5%88%9D%E9%9F%B3%E3%83%9F%E3%82%AF%20%E3%83%A9%E3%83%90%E3%83%BC%E3%82%B9%E3%83%88%E3%83%A9%E3%83%83%E3%83%97%20%28%E3%83%9E%E3%82%B8%E3%82%AB%E3%83%AB%E3%83%9F%E3%83%A9%E3%82%A42023%29",
      "strategy": "official_search",
      "automation_safety": "candidate_provider_script_required",
      "manual_review_required": true,
      "import_template": {
        "catalog_index": 1530,
        "source_url": null,
        "image_url": null,
        "manual_confirmed": false,
        "blocked_until": "exact_goodsmile_product_page_confirmed"
      }
    },
    {
      "catalog_index": 1603,
      "name_ko": "하츠네 미쿠 아크릴 스탠드 (매지컬 미라이 2024)",
      "name_ja": "初音ミク アクリルスタンド (マジカルミライ 2024)",
      "affiliation": "하츠네 미쿠",
      "category": "아크릴 스탠드",
      "query": "初音ミク アクリルスタンド (マジカルミライ 2024)",
      "search_url": "https://www.goodsmile.info/ja/products/search?utf8=%E2%9C%93&search%5Bquery%5D=%E5%88%9D%E9%9F%B3%E3%83%9F%E3%82%AF%20%E3%82%A2%E3%82%AF%E3%83%AA%E3%83%AB%E3%82%B9%E3%82%BF%E3%83%B3%E3%83%89%20%28%E3%83%9E%E3%82%B8%E3%82%AB%E3%83%AB%E3%83%9F%E3%83%A9%E3%82%A4%202024%29",
      "strategy": "official_search",
      "automation_safety": "candidate_provider_script_required",
      "manual_review_required": true,
      "import_template": {
        "catalog_index": 1603,
        "source_url": null,
        "image_url": null,
        "manual_confirmed": false,
        "blocked_until": "exact_goodsmile_product_page_confirmed"
      }
    },
    {
      "catalog_index": 1604,
      "name_ko": "하츠네 미쿠 아크릴 스탠드 (벚꽃 미쿠)",
      "name_ja": "初音ミク アクリルスタンド (桜ミク)",
      "affiliation": "하츠네 미쿠",
      "category": "아크릴 스탠드",
      "query": "初音ミク アクリルスタンド (桜ミク)",
      "search_url": "https://www.goodsmile.info/ja/products/search?utf8=%E2%9C%93&search%5Bquery%5D=%E5%88%9D%E9%9F%B3%E3%83%9F%E3%82%AF%20%E3%82%A2%E3%82%AF%E3%83%AA%E3%83%AB%E3%82%B9%E3%82%BF%E3%83%B3%E3%83%89%20%28%E6%A1%9C%E3%83%9F%E3%82%AF%29",
      "strategy": "official_search",
      "automation_safety": "candidate_provider_script_required",
      "manual_review_required": true,
      "import_template": {
        "catalog_index": 1604,
        "source_url": null,
        "image_url": null,
        "manual_confirmed": false,
        "blocked_until": "exact_goodsmile_product_page_confirmed"
      }
    },
    {
      "catalog_index": 1605,
      "name_ko": "카가미네 린 아크릴 스탠드 (매지컬 미라이)",
      "name_ja": "鏡音リン アクリルスタンド (マジカルミライ)",
      "affiliation": "하츠네 미쿠",
      "category": "아크릴 스탠드",
      "query": "鏡音リン アクリルスタンド (マジカルミライ)",
      "search_url": "https://www.goodsmile.info/ja/products/search?utf8=%E2%9C%93&search%5Bquery%5D=%E9%8F%A1%E9%9F%B3%E3%83%AA%E3%83%B3%20%E3%82%A2%E3%82%AF%E3%83%AA%E3%83%AB%E3%82%B9%E3%82%BF%E3%83%B3%E3%83%89%20%28%E3%83%9E%E3%82%B8%E3%82%AB%E3%83%AB%E3%83%9F%E3%83%A9%E3%82%A4%29",
      "strategy": "official_search",
      "automation_safety": "candidate_provider_script_required",
      "manual_review_required": true,
      "import_template": {
        "catalog_index": 1605,
        "source_url": null,
        "image_url": null,
        "manual_confirmed": false,
        "blocked_until": "exact_goodsmile_product_page_confirmed"
      }
    },
    {
      "catalog_index": 1606,
      "name_ko": "카가미네 렌 아크릴 스탠드 (매지컬 미라이)",
      "name_ja": "鏡音レン アクリルスタンド (マジカルミライ)",
      "affiliation": "하츠네 미쿠",
      "category": "아크릴 스탠드",
      "query": "鏡音レン アクリルスタンド (マジカルミライ)",
      "search_url": "https://www.goodsmile.info/ja/products/search?utf8=%E2%9C%93&search%5Bquery%5D=%E9%8F%A1%E9%9F%B3%E3%83%AC%E3%83%B3%20%E3%82%A2%E3%82%AF%E3%83%AA%E3%83%AB%E3%82%B9%E3%82%BF%E3%83%B3%E3%83%89%20%28%E3%83%9E%E3%82%B8%E3%82%AB%E3%83%AB%E3%83%9F%E3%83%A9%E3%82%A4%29",
      "strategy": "official_search",
      "automation_safety": "candidate_provider_script_required",
      "manual_review_required": true,
      "import_template": {
        "catalog_index": 1606,
        "source_url": null,
        "image_url": null,
        "manual_confirmed": false,
        "blocked_until": "exact_goodsmile_product_page_confirmed"
      }
    },
    {
      "catalog_index": 1607,
      "name_ko": "메구리네 루카 아크릴 스탠드",
      "name_ja": "巡音ルカ アクリルスタンド",
      "affiliation": "하츠네 미쿠",
      "category": "아크릴 스탠드",
      "query": "巡音ルカ アクリルスタンド",
      "search_url": "https://www.goodsmile.info/ja/products/search?utf8=%E2%9C%93&search%5Bquery%5D=%E5%B7%A1%E9%9F%B3%E3%83%AB%E3%82%AB%20%E3%82%A2%E3%82%AF%E3%83%AA%E3%83%AB%E3%82%B9%E3%82%BF%E3%83%B3%E3%83%89",
      "strategy": "official_search",
      "automation_safety": "candidate_provider_script_required",
      "manual_review_required": true,
      "import_template": {
        "catalog_index": 1607,
        "source_url": null,
        "image_url": null,
        "manual_confirmed": false,
        "blocked_until": "exact_goodsmile_product_page_confirmed"
      }
    },
    {
      "catalog_index": 1608,
      "name_ko": "하츠네 미쿠 빅 아크릴 스탠드 (눈 미쿠)",
      "name_ja": "初音ミク ビッグアクリルスタンド (雪ミク)",
      "affiliation": "하츠네 미쿠",
      "category": "아크릴 스탠드",
      "query": "初音ミク ビッグアクリルスタンド (雪ミク)",
      "search_url": "https://www.goodsmile.info/ja/products/search?utf8=%E2%9C%93&search%5Bquery%5D=%E5%88%9D%E9%9F%B3%E3%83%9F%E3%82%AF%20%E3%83%93%E3%83%83%E3%82%B0%E3%82%A2%E3%82%AF%E3%83%AA%E3%83%AB%E3%82%B9%E3%82%BF%E3%83%B3%E3%83%89%20%28%E9%9B%AA%E3%83%9F%E3%82%AF%29",
      "strategy": "official_search",
      "automation_safety": "candidate_provider_script_required",
      "manual_review_required": true,
      "import_template": {
        "catalog_index": 1608,
        "source_url": null,
        "image_url": null,
        "manual_confirmed": false,
        "blocked_until": "exact_goodsmile_product_page_confirmed"
      }
    },
    {
      "catalog_index": 1610,
      "name_ko": "하츠네 미쿠 스탠드 미니 (하나미 시리즈)",
      "name_ja": "初音ミク スタンドミニ (花見シリーズ)",
      "affiliation": "하츠네 미쿠",
      "category": "아크릴 스탠드",
      "query": "初音ミク スタンドミニ (花見シリーズ)",
      "search_url": "https://www.goodsmile.info/ja/products/search?utf8=%E2%9C%93&search%5Bquery%5D=%E5%88%9D%E9%9F%B3%E3%83%9F%E3%82%AF%20%E3%82%B9%E3%82%BF%E3%83%B3%E3%83%89%E3%83%9F%E3%83%8B%20%28%E8%8A%B1%E8%A6%8B%E3%82%B7%E3%83%AA%E3%83%BC%E3%82%BA%29",
      "strategy": "official_search",
      "automation_safety": "candidate_provider_script_required",
      "manual_review_required": true,
      "import_template": {
        "catalog_index": 1610,
        "source_url": null,
        "image_url": null,
        "manual_confirmed": false,
        "blocked_until": "exact_goodsmile_product_page_confirmed"
      }
    },
    {
      "catalog_index": 1634,
      "name_ko": "메이드 인 어비스 아크릴 스탠드 (리코)",
      "name_ja": "メイドインアビス アクリルスタンド (リコ)",
      "affiliation": "메이드 인 어비스",
      "category": "아크릴 스탠드",
      "query": "メイドインアビス アクリルスタンド (リコ)",
      "search_url": "https://www.goodsmile.info/ja/products/search?utf8=%E2%9C%93&search%5Bquery%5D=%E3%83%A1%E3%82%A4%E3%83%89%E3%82%A4%E3%83%B3%E3%82%A2%E3%83%93%E3%82%B9%20%E3%82%A2%E3%82%AF%E3%83%AA%E3%83%AB%E3%82%B9%E3%82%BF%E3%83%B3%E3%83%89%20%28%E3%83%AA%E3%82%B3%29",
      "strategy": "official_search",
      "automation_safety": "candidate_provider_script_required",
      "manual_review_required": true,
      "import_template": {
        "catalog_index": 1634,
        "source_url": null,
        "image_url": null,
        "manual_confirmed": false,
        "blocked_until": "exact_goodsmile_product_page_confirmed"
      }
    },
    {
      "catalog_index": 1635,
      "name_ko": "메이드 인 어비스 아크릴 스탠드 (레그)",
      "name_ja": "メイドインアビス アクリルスタンド (レグ)",
      "affiliation": "메이드 인 어비스",
      "category": "아크릴 스탠드",
      "query": "メイドインアビス アクリルスタンド (レグ)",
      "search_url": "https://www.goodsmile.info/ja/products/search?utf8=%E2%9C%93&search%5Bquery%5D=%E3%83%A1%E3%82%A4%E3%83%89%E3%82%A4%E3%83%B3%E3%82%A2%E3%83%93%E3%82%B9%20%E3%82%A2%E3%82%AF%E3%83%AA%E3%83%AB%E3%82%B9%E3%82%BF%E3%83%B3%E3%83%89%20%28%E3%83%AC%E3%82%B0%29",
      "strategy": "official_search",
      "automation_safety": "candidate_provider_script_required",
      "manual_review_required": true,
      "import_template": {
        "catalog_index": 1635,
        "source_url": null,
        "image_url": null,
        "manual_confirmed": false,
        "blocked_until": "exact_goodsmile_product_page_confirmed"
      }
    },
    {
      "catalog_index": 1636,
      "name_ko": "메이드 인 어비스 아크릴 스탠드 (나나치)",
      "name_ja": "メイドインアビス アクリルスタンド (ナナチ)",
      "affiliation": "메이드 인 어비스",
      "category": "아크릴 스탠드",
      "query": "メイドインアビス アクリルスタンド (ナナチ)",
      "search_url": "https://www.goodsmile.info/ja/products/search?utf8=%E2%9C%93&search%5Bquery%5D=%E3%83%A1%E3%82%A4%E3%83%89%E3%82%A4%E3%83%B3%E3%82%A2%E3%83%93%E3%82%B9%20%E3%82%A2%E3%82%AF%E3%83%AA%E3%83%AB%E3%82%B9%E3%82%BF%E3%83%B3%E3%83%89%20%28%E3%83%8A%E3%83%8A%E3%83%81%29",
      "strategy": "official_search",
      "automation_safety": "candidate_provider_script_required",
      "manual_review_required": true,
      "import_template": {
        "catalog_index": 1636,
        "source_url": null,
        "image_url": null,
        "manual_confirmed": false,
        "blocked_until": "exact_goodsmile_product_page_confirmed"
      }
    },
    {
      "catalog_index": 1638,
      "name_ko": "메이드 인 어비스 빅 아크릴 스탠드 (나나치)",
      "name_ja": "メイドインアビス ビッグアクリルスタンド (ナナチ)",
      "affiliation": "메이드 인 어비스",
      "category": "아크릴 스탠드",
      "query": "メイドインアビス ビッグアクリルスタンド (ナナチ)",
      "search_url": "https://www.goodsmile.info/ja/products/search?utf8=%E2%9C%93&search%5Bquery%5D=%E3%83%A1%E3%82%A4%E3%83%89%E3%82%A4%E3%83%B3%E3%82%A2%E3%83%93%E3%82%B9%20%E3%83%93%E3%83%83%E3%82%B0%E3%82%A2%E3%82%AF%E3%83%AA%E3%83%AB%E3%82%B9%E3%82%BF%E3%83%B3%E3%83%89%20%28%E3%83%8A%E3%83%8A%E3%83%81%29",
      "strategy": "official_search",
      "automation_safety": "candidate_provider_script_required",
      "manual_review_required": true,
      "import_template": {
        "catalog_index": 1638,
        "source_url": null,
        "image_url": null,
        "manual_confirmed": false,
        "blocked_until": "exact_goodsmile_product_page_confirmed"
      }
    },
    {
      "catalog_index": 1763,
      "name_ko": "하츠네 미쿠 트레이딩 캔뱃지 오리지널",
      "name_ja": "初音ミク トレーディング缶バッジ オリジナル",
      "affiliation": "하츠네 미쿠",
      "category": "캔뱃지",
      "query": "初音ミク トレーディング缶バッジ オリジナル",
      "search_url": "https://www.goodsmile.info/ja/products/search?utf8=%E2%9C%93&search%5Bquery%5D=%E5%88%9D%E9%9F%B3%E3%83%9F%E3%82%AF%20%E3%83%88%E3%83%AC%E3%83%BC%E3%83%87%E3%82%A3%E3%83%B3%E3%82%B0%E7%BC%B6%E3%83%90%E3%83%83%E3%82%B8%20%E3%82%AA%E3%83%AA%E3%82%B8%E3%83%8A%E3%83%AB",
      "strategy": "official_search",
      "automation_safety": "candidate_provider_script_required",
      "manual_review_required": true,
      "import_template": {
        "catalog_index": 1763,
        "source_url": null,
        "image_url": null,
        "manual_confirmed": false,
        "blocked_until": "exact_goodsmile_product_page_confirmed"
      }
    },
    {
      "catalog_index": 1764,
      "name_ko": "하츠네 미쿠 트레이딩 캔뱃지 매지컬 미라이",
      "name_ja": "初音ミク トレーディング缶バッジ マジカルミライ",
      "affiliation": "하츠네 미쿠",
      "category": "캔뱃지",
      "query": "初音ミク トレーディング缶バッジ マジカルミライ",
      "search_url": "https://www.goodsmile.info/ja/products/search?utf8=%E2%9C%93&search%5Bquery%5D=%E5%88%9D%E9%9F%B3%E3%83%9F%E3%82%AF%20%E3%83%88%E3%83%AC%E3%83%BC%E3%83%87%E3%82%A3%E3%83%B3%E3%82%B0%E7%BC%B6%E3%83%90%E3%83%83%E3%82%B8%20%E3%83%9E%E3%82%B8%E3%82%AB%E3%83%AB%E3%83%9F%E3%83%A9%E3%82%A4",
      "strategy": "official_search",
      "automation_safety": "candidate_provider_script_required",
      "manual_review_required": true,
      "import_template": {
        "catalog_index": 1764,
        "source_url": null,
        "image_url": null,
        "manual_confirmed": false,
        "blocked_until": "exact_goodsmile_product_page_confirmed"
      }
    },
    {
      "catalog_index": 1765,
      "name_ko": "하츠네 미쿠 트레이딩 캔뱃지 눈 미쿠",
      "name_ja": "初音ミク トレーディング缶バッジ 雪ミク",
      "affiliation": "하츠네 미쿠",
      "category": "캔뱃지",
      "query": "初音ミク トレーディング缶バッジ 雪ミク",
      "search_url": "https://www.goodsmile.info/ja/products/search?utf8=%E2%9C%93&search%5Bquery%5D=%E5%88%9D%E9%9F%B3%E3%83%9F%E3%82%AF%20%E3%83%88%E3%83%AC%E3%83%BC%E3%83%87%E3%82%A3%E3%83%B3%E3%82%B0%E7%BC%B6%E3%83%90%E3%83%83%E3%82%B8%20%E9%9B%AA%E3%83%9F%E3%82%AF",
      "strategy": "official_search",
      "automation_safety": "candidate_provider_script_required",
      "manual_review_required": true,
      "import_template": {
        "catalog_index": 1765,
        "source_url": null,
        "image_url": null,
        "manual_confirmed": false,
        "blocked_until": "exact_goodsmile_product_page_confirmed"
      }
    },
    {
      "catalog_index": 1766,
      "name_ko": "하츠네 미쿠 트레이딩 캔뱃지 벚꽃 미쿠",
      "name_ja": "初音ミク トレーディング缶バッジ 桜ミク",
      "affiliation": "하츠네 미쿠",
      "category": "캔뱃지",
      "query": "初音ミク トレーディング缶バッジ 桜ミク",
      "search_url": "https://www.goodsmile.info/ja/products/search?utf8=%E2%9C%93&search%5Bquery%5D=%E5%88%9D%E9%9F%B3%E3%83%9F%E3%82%AF%20%E3%83%88%E3%83%AC%E3%83%BC%E3%83%87%E3%82%A3%E3%83%B3%E3%82%B0%E7%BC%B6%E3%83%90%E3%83%83%E3%82%B8%20%E6%A1%9C%E3%83%9F%E3%82%AF",
      "strategy": "official_search",
      "automation_safety": "candidate_provider_script_required",
      "manual_review_required": true,
      "import_template": {
        "catalog_index": 1766,
        "source_url": null,
        "image_url": null,
        "manual_confirmed": false,
        "blocked_until": "exact_goodsmile_product_page_confirmed"
      }
    },
    {
      "catalog_index": 1767,
      "name_ko": "하츠네 미쿠 메탈릭 캔뱃지 오리지널",
      "name_ja": "初音ミク メタリック缶バッジ オリジナル",
      "affiliation": "하츠네 미쿠",
      "category": "캔뱃지",
      "query": "初音ミク メタリック缶バッジ オリジナル",
      "search_url": "https://www.goodsmile.info/ja/products/search?utf8=%E2%9C%93&search%5Bquery%5D=%E5%88%9D%E9%9F%B3%E3%83%9F%E3%82%AF%20%E3%83%A1%E3%82%BF%E3%83%AA%E3%83%83%E3%82%AF%E7%BC%B6%E3%83%90%E3%83%83%E3%82%B8%20%E3%82%AA%E3%83%AA%E3%82%B8%E3%83%8A%E3%83%AB",
      "strategy": "official_search",
      "automation_safety": "candidate_provider_script_required",
      "manual_review_required": true,
      "import_template": {
        "catalog_index": 1767,
        "source_url": null,
        "image_url": null,
        "manual_confirmed": false,
        "blocked_until": "exact_goodsmile_product_page_confirmed"
      }
    },
    {
      "catalog_index": 1768,
      "name_ko": "하츠네 미쿠 빅 캔뱃지 매지컬 미라이",
      "name_ja": "初音ミク BIG缶バッジ マジカルミライ",
      "affiliation": "하츠네 미쿠",
      "category": "캔뱃지",
      "query": "初音ミク BIG缶バッジ マジカルミライ",
      "search_url": "https://www.goodsmile.info/ja/products/search?utf8=%E2%9C%93&search%5Bquery%5D=%E5%88%9D%E9%9F%B3%E3%83%9F%E3%82%AF%20BIG%E7%BC%B6%E3%83%90%E3%83%83%E3%82%B8%20%E3%83%9E%E3%82%B8%E3%82%AB%E3%83%AB%E3%83%9F%E3%83%A9%E3%82%A4",
      "strategy": "official_search",
      "automation_safety": "candidate_provider_script_required",
      "manual_review_required": true,
      "import_template": {
        "catalog_index": 1768,
        "source_url": null,
        "image_url": null,
        "manual_confirmed": false,
        "blocked_until": "exact_goodsmile_product_page_confirmed"
      }
    },
    {
      "catalog_index": 1772,
      "name_ko": "하츠네 미쿠 클리어 파일 A4 매지컬 미라이",
      "name_ja": "初音ミク クリアファイルA4 マジカルミライ",
      "affiliation": "하츠네 미쿠",
      "category": "문구",
      "query": "初音ミク クリアファイルA4 マジカルミライ",
      "search_url": "https://www.goodsmile.info/ja/products/search?utf8=%E2%9C%93&search%5Bquery%5D=%E5%88%9D%E9%9F%B3%E3%83%9F%E3%82%AF%20%E3%82%AF%E3%83%AA%E3%82%A2%E3%83%95%E3%82%A1%E3%82%A4%E3%83%ABA4%20%E3%83%9E%E3%82%B8%E3%82%AB%E3%83%AB%E3%83%9F%E3%83%A9%E3%82%A4",
      "strategy": "official_search",
      "automation_safety": "candidate_provider_script_required",
      "manual_review_required": true,
      "import_template": {
        "catalog_index": 1772,
        "source_url": null,
        "image_url": null,
        "manual_confirmed": false,
        "blocked_until": "exact_goodsmile_product_page_confirmed"
      }
    },
    {
      "catalog_index": 1774,
      "name_ko": "하츠네 미쿠 일러스트 카드 컬렉션 오리지널",
      "name_ja": "初音ミク イラストカードコレクション オリジナル",
      "affiliation": "하츠네 미쿠",
      "category": "문구",
      "query": "初音ミク イラストカードコレクション オリジナル",
      "search_url": "https://www.goodsmile.info/ja/products/search?utf8=%E2%9C%93&search%5Bquery%5D=%E5%88%9D%E9%9F%B3%E3%83%9F%E3%82%AF%20%E3%82%A4%E3%83%A9%E3%82%B9%E3%83%88%E3%82%AB%E3%83%BC%E3%83%89%E3%82%B3%E3%83%AC%E3%82%AF%E3%82%B7%E3%83%A7%E3%83%B3%20%E3%82%AA%E3%83%AA%E3%82%B8%E3%83%8A%E3%83%AB",
      "strategy": "official_search",
      "automation_safety": "candidate_provider_script_required",
      "manual_review_required": true,
      "import_template": {
        "catalog_index": 1774,
        "source_url": null,
        "image_url": null,
        "manual_confirmed": false,
        "blocked_until": "exact_goodsmile_product_page_confirmed"
      }
    },
    {
      "catalog_index": 1809,
      "name_ko": "하츠네 미쿠 매지컬 미라이 2024 머그컵",
      "name_ja": "初音ミク マジカルミライ 2024 マグカップ",
      "affiliation": "하츠네 미쿠",
      "category": "머그컵",
      "query": "初音ミク マジカルミライ 2024 マグカップ",
      "search_url": "https://www.goodsmile.info/ja/products/search?utf8=%E2%9C%93&search%5Bquery%5D=%E5%88%9D%E9%9F%B3%E3%83%9F%E3%82%AF%20%E3%83%9E%E3%82%B8%E3%82%AB%E3%83%AB%E3%83%9F%E3%83%A9%E3%82%A4%202024%20%E3%83%9E%E3%82%B0%E3%82%AB%E3%83%83%E3%83%97",
      "strategy": "official_search",
      "automation_safety": "candidate_provider_script_required",
      "manual_review_required": true,
      "import_template": {
        "catalog_index": 1809,
        "source_url": null,
        "image_url": null,
        "manual_confirmed": false,
        "blocked_until": "exact_goodsmile_product_page_confirmed"
      }
    },
    {
      "catalog_index": 1810,
      "name_ko": "하츠네 미쿠 매지컬 미라이 2023 타올",
      "name_ja": "初音ミク マジカルミライ 2023 タオル",
      "affiliation": "하츠네 미쿠",
      "category": "타월",
      "query": "初音ミク マジカルミライ 2023 タオル",
      "search_url": "https://www.goodsmile.info/ja/products/search?utf8=%E2%9C%93&search%5Bquery%5D=%E5%88%9D%E9%9F%B3%E3%83%9F%E3%82%AF%20%E3%83%9E%E3%82%B8%E3%82%AB%E3%83%AB%E3%83%9F%E3%83%A9%E3%82%A4%202023%20%E3%82%BF%E3%82%AA%E3%83%AB",
      "strategy": "official_search",
      "automation_safety": "candidate_provider_script_required",
      "manual_review_required": true,
      "import_template": {
        "catalog_index": 1810,
        "source_url": null,
        "image_url": null,
        "manual_confirmed": false,
        "blocked_until": "exact_goodsmile_product_page_confirmed"
      }
    },
    {
      "catalog_index": 1811,
      "name_ko": "하츠네 미쿠 매지컬 미라이 펜라이트",
      "name_ja": "初音ミク マジカルミライ ペンライト",
      "affiliation": "하츠네 미쿠",
      "category": "응원봉",
      "query": "初音ミク マジカルミライ ペンライト",
      "search_url": "https://www.goodsmile.info/ja/products/search?utf8=%E2%9C%93&search%5Bquery%5D=%E5%88%9D%E9%9F%B3%E3%83%9F%E3%82%AF%20%E3%83%9E%E3%82%B8%E3%82%AB%E3%83%AB%E3%83%9F%E3%83%A9%E3%82%A4%20%E3%83%9A%E3%83%B3%E3%83%A9%E3%82%A4%E3%83%88",
      "strategy": "official_search",
      "automation_safety": "candidate_provider_script_required",
      "manual_review_required": true,
      "import_template": {
        "catalog_index": 1811,
        "source_url": null,
        "image_url": null,
        "manual_confirmed": false,
        "blocked_until": "exact_goodsmile_product_page_confirmed"
      }
    },
    {
      "catalog_index": 1812,
      "name_ko": "하츠네 미쿠 매지컬 미라이 토트백",
      "name_ja": "初音ミク マジカルミライ トートバッグ",
      "affiliation": "하츠네 미쿠",
      "category": "가방",
      "query": "初音ミク マジカルミライ トートバッグ",
      "search_url": "https://www.goodsmile.info/ja/products/search?utf8=%E2%9C%93&search%5Bquery%5D=%E5%88%9D%E9%9F%B3%E3%83%9F%E3%82%AF%20%E3%83%9E%E3%82%B8%E3%82%AB%E3%83%AB%E3%83%9F%E3%83%A9%E3%82%A4%20%E3%83%88%E3%83%BC%E3%83%88%E3%83%90%E3%83%83%E3%82%B0",
      "strategy": "official_search",
      "automation_safety": "candidate_provider_script_required",
      "manual_review_required": true,
      "import_template": {
        "catalog_index": 1812,
        "source_url": null,
        "image_url": null,
        "manual_confirmed": false,
        "blocked_until": "exact_goodsmile_product_page_confirmed"
      }
    },
    {
      "catalog_index": 1813,
      "name_ko": "하츠네 미쿠 매지컬 미라이 우치와",
      "name_ja": "初音ミク マジカルミライ うちわ",
      "affiliation": "하츠네 미쿠",
      "category": "응원용품",
      "query": "初音ミク マジカルミライ うちわ",
      "search_url": "https://www.goodsmile.info/ja/products/search?utf8=%E2%9C%93&search%5Bquery%5D=%E5%88%9D%E9%9F%B3%E3%83%9F%E3%82%AF%20%E3%83%9E%E3%82%B8%E3%82%AB%E3%83%AB%E3%83%9F%E3%83%A9%E3%82%A4%20%E3%81%86%E3%81%A1%E3%82%8F",
      "strategy": "official_search",
      "automation_safety": "candidate_provider_script_required",
      "manual_review_required": true,
      "import_template": {
        "catalog_index": 1813,
        "source_url": null,
        "image_url": null,
        "manual_confirmed": false,
        "blocked_until": "exact_goodsmile_product_page_confirmed"
      }
    },
    {
      "catalog_index": 1814,
      "name_ko": "하츠네 미쿠 매지컬 미라이 클리어 보틀",
      "name_ja": "初音ミク マジカルミライ クリアボトル",
      "affiliation": "하츠네 미쿠",
      "category": "생활잡화",
      "query": "初音ミク マジカルミライ クリアボトル",
      "search_url": "https://www.goodsmile.info/ja/products/search?utf8=%E2%9C%93&search%5Bquery%5D=%E5%88%9D%E9%9F%B3%E3%83%9F%E3%82%AF%20%E3%83%9E%E3%82%B8%E3%82%AB%E3%83%AB%E3%83%9F%E3%83%A9%E3%82%A4%20%E3%82%AF%E3%83%AA%E3%82%A2%E3%83%9C%E3%83%88%E3%83%AB",
      "strategy": "official_search",
      "automation_safety": "candidate_provider_script_required",
      "manual_review_required": true,
      "import_template": {
        "catalog_index": 1814,
        "source_url": null,
        "image_url": null,
        "manual_confirmed": false,
        "blocked_until": "exact_goodsmile_product_page_confirmed"
      }
    },
    {
      "catalog_index": 1815,
      "name_ko": "하츠네 미쿠 라이브 한정 펜라이트 2024",
      "name_ja": "初音ミク ライブ限定 ペンライト 2024",
      "affiliation": "하츠네 미쿠",
      "category": "응원봉",
      "query": "初音ミク ライブ限定 ペンライト 2024",
      "search_url": "https://www.goodsmile.info/ja/products/search?utf8=%E2%9C%93&search%5Bquery%5D=%E5%88%9D%E9%9F%B3%E3%83%9F%E3%82%AF%20%E3%83%A9%E3%82%A4%E3%83%96%E9%99%90%E5%AE%9A%20%E3%83%9A%E3%83%B3%E3%83%A9%E3%82%A4%E3%83%88%202024",
      "strategy": "official_search",
      "automation_safety": "candidate_provider_script_required",
      "manual_review_required": true,
      "import_template": {
        "catalog_index": 1815,
        "source_url": null,
        "image_url": null,
        "manual_confirmed": false,
        "blocked_until": "exact_goodsmile_product_page_confirmed"
      }
    },
    {
      "catalog_index": 1816,
      "name_ko": "카가미네 린 머그컵",
      "name_ja": "鏡音リン マグカップ",
      "affiliation": "하츠네 미쿠",
      "category": "머그컵",
      "query": "鏡音リン マグカップ",
      "search_url": "https://www.goodsmile.info/ja/products/search?utf8=%E2%9C%93&search%5Bquery%5D=%E9%8F%A1%E9%9F%B3%E3%83%AA%E3%83%B3%20%E3%83%9E%E3%82%B0%E3%82%AB%E3%83%83%E3%83%97",
      "strategy": "official_search",
      "automation_safety": "candidate_provider_script_required",
      "manual_review_required": true,
      "import_template": {
        "catalog_index": 1816,
        "source_url": null,
        "image_url": null,
        "manual_confirmed": false,
        "blocked_until": "exact_goodsmile_product_page_confirmed"
      }
    },
    {
      "catalog_index": 1881,
      "name_ko": "POP UP PARADE 카이저",
      "name_ja": "POP UP PARADE ミヒャエル・カイザー",
      "affiliation": "블루록",
      "category": "피규어",
      "query": "POP UP PARADE ミヒャエル・カイザー",
      "search_url": "https://www.goodsmile.info/ja/products/search?utf8=%E2%9C%93&search%5Bquery%5D=POP%20UP%20PARADE%20%E3%83%9F%E3%83%92%E3%83%A3%E3%82%A8%E3%83%AB%E3%83%BB%E3%82%AB%E3%82%A4%E3%82%B6%E3%83%BC",
      "strategy": "official_search",
      "automation_safety": "candidate_provider_script_required",
      "manual_review_required": true,
      "import_template": {
        "catalog_index": 1881,
        "source_url": null,
        "image_url": null,
        "manual_confirmed": false,
        "blocked_until": "exact_goodsmile_product_page_confirmed"
      }
    },
    {
      "catalog_index": 1882,
      "name_ko": "POP UP PARADE 시도 료스케",
      "name_ja": "POP UP PARADE 士道龍聖",
      "affiliation": "블루록",
      "category": "피규어",
      "query": "POP UP PARADE 士道龍聖",
      "search_url": "https://www.goodsmile.info/ja/products/search?utf8=%E2%9C%93&search%5Bquery%5D=POP%20UP%20PARADE%20%E5%A3%AB%E9%81%93%E9%BE%8D%E8%81%96",
      "strategy": "official_search",
      "automation_safety": "candidate_provider_script_required",
      "manual_review_required": true,
      "import_template": {
        "catalog_index": 1882,
        "source_url": null,
        "image_url": null,
        "manual_confirmed": false,
        "blocked_until": "exact_goodsmile_product_page_confirmed"
      }
    },
    {
      "catalog_index": 1883,
      "name_ko": "POP UP PARADE 미코토",
      "name_ja": "POP UP PARADE 御影玲王",
      "affiliation": "블루록",
      "category": "피규어",
      "query": "POP UP PARADE 御影玲王",
      "search_url": "https://www.goodsmile.info/ja/products/search?utf8=%E2%9C%93&search%5Bquery%5D=POP%20UP%20PARADE%20%E5%BE%A1%E5%BD%B1%E7%8E%B2%E7%8E%8B",
      "strategy": "official_search",
      "automation_safety": "candidate_provider_script_required",
      "manual_review_required": true,
      "import_template": {
        "catalog_index": 1883,
        "source_url": null,
        "image_url": null,
        "manual_confirmed": false,
        "blocked_until": "exact_goodsmile_product_page_confirmed"
      }
    },
    {
      "catalog_index": 1884,
      "name_ko": "POP UP PARADE 치기리",
      "name_ja": "POP UP PARADE 千切豹馬",
      "affiliation": "블루록",
      "category": "피규어",
      "query": "POP UP PARADE 千切豹馬",
      "search_url": "https://www.goodsmile.info/ja/products/search?utf8=%E2%9C%93&search%5Bquery%5D=POP%20UP%20PARADE%20%E5%8D%83%E5%88%87%E8%B1%B9%E9%A6%AC",
      "strategy": "official_search",
      "automation_safety": "candidate_provider_script_required",
      "manual_review_required": true,
      "import_template": {
        "catalog_index": 1884,
        "source_url": null,
        "image_url": null,
        "manual_confirmed": false,
        "blocked_until": "exact_goodsmile_product_page_confirmed"
      }
    },
    {
      "catalog_index": 1904,
      "name_ko": "POP UP PARADE 야마다 료",
      "name_ja": "POP UP PARADE 山田リョウ",
      "affiliation": "봇치 더 록",
      "category": "피규어",
      "query": "POP UP PARADE 山田リョウ",
      "search_url": "https://www.goodsmile.info/ja/products/search?utf8=%E2%9C%93&search%5Bquery%5D=POP%20UP%20PARADE%20%E5%B1%B1%E7%94%B0%E3%83%AA%E3%83%A7%E3%82%A6",
      "strategy": "official_search",
      "automation_safety": "candidate_provider_script_required",
      "manual_review_required": true,
      "import_template": {
        "catalog_index": 1904,
        "source_url": null,
        "image_url": null,
        "manual_confirmed": false,
        "blocked_until": "exact_goodsmile_product_page_confirmed"
      }
    },
    {
      "catalog_index": 1905,
      "name_ko": "POP UP PARADE 키타 이쿠요",
      "name_ja": "POP UP PARADE 喜多郁代",
      "affiliation": "봇치 더 록",
      "category": "피규어",
      "query": "POP UP PARADE 喜多郁代",
      "search_url": "https://www.goodsmile.info/ja/products/search?utf8=%E2%9C%93&search%5Bquery%5D=POP%20UP%20PARADE%20%E5%96%9C%E5%A4%9A%E9%83%81%E4%BB%A3",
      "strategy": "official_search",
      "automation_safety": "candidate_provider_script_required",
      "manual_review_required": true,
      "import_template": {
        "catalog_index": 1905,
        "source_url": null,
        "image_url": null,
        "manual_confirmed": false,
        "blocked_until": "exact_goodsmile_product_page_confirmed"
      }
    },
    {
      "catalog_index": 1920,
      "name_ko": "POP UP PARADE 천사 악마",
      "name_ja": "POP UP PARADE 天使の悪魔",
      "affiliation": "체인소 맨",
      "category": "피규어",
      "query": "POP UP PARADE 天使の悪魔",
      "search_url": "https://www.goodsmile.info/ja/products/search?utf8=%E2%9C%93&search%5Bquery%5D=POP%20UP%20PARADE%20%E5%A4%A9%E4%BD%BF%E3%81%AE%E6%82%AA%E9%AD%94",
      "strategy": "official_search",
      "automation_safety": "candidate_provider_script_required",
      "manual_review_required": true,
      "import_template": {
        "catalog_index": 1920,
        "source_url": null,
        "image_url": null,
        "manual_confirmed": false,
        "blocked_until": "exact_goodsmile_product_page_confirmed"
      }
    },
    {
      "catalog_index": 1922,
      "name_ko": "POP UP PARADE 우솝",
      "name_ja": "POP UP PARADE ウソップ",
      "affiliation": "원피스",
      "category": "피규어",
      "query": "POP UP PARADE ウソップ",
      "search_url": "https://www.goodsmile.info/ja/products/search?utf8=%E2%9C%93&search%5Bquery%5D=POP%20UP%20PARADE%20%E3%82%A6%E3%82%BD%E3%83%83%E3%83%97",
      "strategy": "official_search",
      "automation_safety": "candidate_provider_script_required",
      "manual_review_required": true,
      "import_template": {
        "catalog_index": 1922,
        "source_url": null,
        "image_url": null,
        "manual_confirmed": false,
        "blocked_until": "exact_goodsmile_product_page_confirmed"
      }
    },
    {
      "catalog_index": 1923,
      "name_ko": "POP UP PARADE 토니토니 쵸파",
      "name_ja": "POP UP PARADE トニートニー・チョッパー",
      "affiliation": "원피스",
      "category": "피규어",
      "query": "POP UP PARADE トニートニー・チョッパー",
      "search_url": "https://www.goodsmile.info/ja/products/search?utf8=%E2%9C%93&search%5Bquery%5D=POP%20UP%20PARADE%20%E3%83%88%E3%83%8B%E3%83%BC%E3%83%88%E3%83%8B%E3%83%BC%E3%83%BB%E3%83%81%E3%83%A7%E3%83%83%E3%83%91%E3%83%BC",
      "strategy": "official_search",
      "automation_safety": "candidate_provider_script_required",
      "manual_review_required": true,
      "import_template": {
        "catalog_index": 1923,
        "source_url": null,
        "image_url": null,
        "manual_confirmed": false,
        "blocked_until": "exact_goodsmile_product_page_confirmed"
      }
    },
    {
      "catalog_index": 1924,
      "name_ko": "POP UP PARADE 니코 로빈",
      "name_ja": "POP UP PARADE ニコ・ロビン",
      "affiliation": "원피스",
      "category": "피규어",
      "query": "POP UP PARADE ニコ・ロビン",
      "search_url": "https://www.goodsmile.info/ja/products/search?utf8=%E2%9C%93&search%5Bquery%5D=POP%20UP%20PARADE%20%E3%83%8B%E3%82%B3%E3%83%BB%E3%83%AD%E3%83%93%E3%83%B3",
      "strategy": "official_search",
      "automation_safety": "candidate_provider_script_required",
      "manual_review_required": true,
      "import_template": {
        "catalog_index": 1924,
        "source_url": null,
        "image_url": null,
        "manual_confirmed": false,
        "blocked_until": "exact_goodsmile_product_page_confirmed"
      }
    },
    {
      "catalog_index": 1925,
      "name_ko": "POP UP PARADE 프랑키",
      "name_ja": "POP UP PARADE フランキー",
      "affiliation": "원피스",
      "category": "피규어",
      "query": "POP UP PARADE フランキー",
      "search_url": "https://www.goodsmile.info/ja/products/search?utf8=%E2%9C%93&search%5Bquery%5D=POP%20UP%20PARADE%20%E3%83%95%E3%83%A9%E3%83%B3%E3%82%AD%E3%83%BC",
      "strategy": "official_search",
      "automation_safety": "candidate_provider_script_required",
      "manual_review_required": true,
      "import_template": {
        "catalog_index": 1925,
        "source_url": null,
        "image_url": null,
        "manual_confirmed": false,
        "blocked_until": "exact_goodsmile_product_page_confirmed"
      }
    },
    {
      "catalog_index": 1926,
      "name_ko": "POP UP PARADE 브룩",
      "name_ja": "POP UP PARADE ブルック",
      "affiliation": "원피스",
      "category": "피규어",
      "query": "POP UP PARADE ブルック",
      "search_url": "https://www.goodsmile.info/ja/products/search?utf8=%E2%9C%93&search%5Bquery%5D=POP%20UP%20PARADE%20%E3%83%96%E3%83%AB%E3%83%83%E3%82%AF",
      "strategy": "official_search",
      "automation_safety": "candidate_provider_script_required",
      "manual_review_required": true,
      "import_template": {
        "catalog_index": 1926,
        "source_url": null,
        "image_url": null,
        "manual_confirmed": false,
        "blocked_until": "exact_goodsmile_product_page_confirmed"
      }
    },
    {
      "catalog_index": 1927,
      "name_ko": "POP UP PARADE 징베",
      "name_ja": "POP UP PARADE ジンベエ",
      "affiliation": "원피스",
      "category": "피규어",
      "query": "POP UP PARADE ジンベエ",
      "search_url": "https://www.goodsmile.info/ja/products/search?utf8=%E2%9C%93&search%5Bquery%5D=POP%20UP%20PARADE%20%E3%82%B8%E3%83%B3%E3%83%99%E3%82%A8",
      "strategy": "official_search",
      "automation_safety": "candidate_provider_script_required",
      "manual_review_required": true,
      "import_template": {
        "catalog_index": 1927,
        "source_url": null,
        "image_url": null,
        "manual_confirmed": false,
        "blocked_until": "exact_goodsmile_product_page_confirmed"
      }
    },
    {
      "catalog_index": 1928,
      "name_ko": "POP UP PARADE 사보",
      "name_ja": "POP UP PARADE サボ",
      "affiliation": "원피스",
      "category": "피규어",
      "query": "POP UP PARADE サボ",
      "search_url": "https://www.goodsmile.info/ja/products/search?utf8=%E2%9C%93&search%5Bquery%5D=POP%20UP%20PARADE%20%E3%82%B5%E3%83%9C",
      "strategy": "official_search",
      "automation_safety": "candidate_provider_script_required",
      "manual_review_required": true,
      "import_template": {
        "catalog_index": 1928,
        "source_url": null,
        "image_url": null,
        "manual_confirmed": false,
        "blocked_until": "exact_goodsmile_product_page_confirmed"
      }
    },
    {
      "catalog_index": 1949,
      "name_ko": "POP UP PARADE 미카사 아커만",
      "name_ja": "POP UP PARADE ミカサ・アッカーマン",
      "affiliation": "진격의 거인",
      "category": "피규어",
      "query": "POP UP PARADE ミカサ・アッカーマン",
      "search_url": "https://www.goodsmile.info/ja/products/search?utf8=%E2%9C%93&search%5Bquery%5D=POP%20UP%20PARADE%20%E3%83%9F%E3%82%AB%E3%82%B5%E3%83%BB%E3%82%A2%E3%83%83%E3%82%AB%E3%83%BC%E3%83%9E%E3%83%B3",
      "strategy": "official_search",
      "automation_safety": "candidate_provider_script_required",
      "manual_review_required": true,
      "import_template": {
        "catalog_index": 1949,
        "source_url": null,
        "image_url": null,
        "manual_confirmed": false,
        "blocked_until": "exact_goodsmile_product_page_confirmed"
      }
    },
    {
      "catalog_index": 1983,
      "name_ko": "POP UP PARADE 쿠로카와 아카네",
      "name_ja": "POP UP PARADE 黒川あかね",
      "affiliation": "최애의 아이",
      "category": "피규어",
      "query": "POP UP PARADE 黒川あかね",
      "search_url": "https://www.goodsmile.info/ja/products/search?utf8=%E2%9C%93&search%5Bquery%5D=POP%20UP%20PARADE%20%E9%BB%92%E5%B7%9D%E3%81%82%E3%81%8B%E3%81%AD",
      "strategy": "official_search",
      "automation_safety": "candidate_provider_script_required",
      "manual_review_required": true,
      "import_template": {
        "catalog_index": 1983,
        "source_url": null,
        "image_url": null,
        "manual_confirmed": false,
        "blocked_until": "exact_goodsmile_product_page_confirmed"
      }
    },
    {
      "catalog_index": 2010,
      "name_ko": "POP UP PARADE 베아트리스",
      "name_ja": "POP UP PARADE ベアトリス",
      "affiliation": "리제로",
      "category": "피규어",
      "query": "POP UP PARADE ベアトリス",
      "search_url": "https://www.goodsmile.info/ja/products/search?utf8=%E2%9C%93&search%5Bquery%5D=POP%20UP%20PARADE%20%E3%83%99%E3%82%A2%E3%83%88%E3%83%AA%E3%82%B9",
      "strategy": "official_search",
      "automation_safety": "candidate_provider_script_required",
      "manual_review_required": true,
      "import_template": {
        "catalog_index": 2010,
        "source_url": null,
        "image_url": null,
        "manual_confirmed": false,
        "blocked_until": "exact_goodsmile_product_page_confirmed"
      }
    },
    {
      "catalog_index": 2038,
      "name_ko": "넨도로이드 마히토",
      "name_ja": "ねんどろいど 真人",
      "affiliation": "주술회전",
      "category": "피규어",
      "query": "ねんどろいど 真人",
      "search_url": "https://www.goodsmile.info/ja/products/search?utf8=%E2%9C%93&search%5Bquery%5D=%E3%81%AD%E3%82%93%E3%81%A9%E3%82%8D%E3%81%84%E3%81%A9%20%E7%9C%9F%E4%BA%BA",
      "strategy": "official_search",
      "automation_safety": "candidate_provider_script_required",
      "manual_review_required": true,
      "import_template": {
        "catalog_index": 2038,
        "source_url": null,
        "image_url": null,
        "manual_confirmed": false,
        "blocked_until": "exact_goodsmile_product_page_confirmed"
      }
    },
    {
      "catalog_index": 2039,
      "name_ko": "POP UP PARADE 마히토",
      "name_ja": "POP UP PARADE 真人",
      "affiliation": "주술회전",
      "category": "피규어",
      "query": "POP UP PARADE 真人",
      "search_url": "https://www.goodsmile.info/ja/products/search?utf8=%E2%9C%93&search%5Bquery%5D=POP%20UP%20PARADE%20%E7%9C%9F%E4%BA%BA",
      "strategy": "official_search",
      "automation_safety": "candidate_provider_script_required",
      "manual_review_required": true,
      "import_template": {
        "catalog_index": 2039,
        "source_url": null,
        "image_url": null,
        "manual_confirmed": false,
        "blocked_until": "exact_goodsmile_product_page_confirmed"
      }
    },
    {
      "catalog_index": 2053,
      "name_ko": "넨도로이드 시즈에 이자와",
      "name_ja": "ねんどろいど 井沢静江",
      "affiliation": "전생슬",
      "category": "피규어",
      "query": "ねんどろいど 井沢静江",
      "search_url": "https://www.goodsmile.info/ja/products/search?utf8=%E2%9C%93&search%5Bquery%5D=%E3%81%AD%E3%82%93%E3%81%A9%E3%82%8D%E3%81%84%E3%81%A9%20%E4%BA%95%E6%B2%A2%E9%9D%99%E6%B1%9F",
      "strategy": "official_search",
      "automation_safety": "candidate_provider_script_required",
      "manual_review_required": true,
      "import_template": {
        "catalog_index": 2053,
        "source_url": null,
        "image_url": null,
        "manual_confirmed": false,
        "blocked_until": "exact_goodsmile_product_page_confirmed"
      }
    },
    {
      "catalog_index": 2058,
      "name_ko": "POP UP PARADE 디아블로",
      "name_ja": "POP UP PARADE ディアブロ",
      "affiliation": "전생슬",
      "category": "피규어",
      "query": "POP UP PARADE ディアブロ",
      "search_url": "https://www.goodsmile.info/ja/products/search?utf8=%E2%9C%93&search%5Bquery%5D=POP%20UP%20PARADE%20%E3%83%87%E3%82%A3%E3%82%A2%E3%83%96%E3%83%AD",
      "strategy": "official_search",
      "automation_safety": "candidate_provider_script_required",
      "manual_review_required": true,
      "import_template": {
        "catalog_index": 2058,
        "source_url": null,
        "image_url": null,
        "manual_confirmed": false,
        "blocked_until": "exact_goodsmile_product_page_confirmed"
      }
    }
  ],
  "missing_queue_samples": [],
  "automation_policy": {
    "auto_apply_catalog_changes": false,
    "requires_exact_product_identity": true,
    "requires_exact_goodsmile_product_page": true,
    "requires_human_review_before_source_or_image_attachment": true
  }
}
